{
  "market_prices": {
    "フルラ 財布": {
      "condition_excellent": 11000,
      "condition_good": 5500,
      "shipping_fee_est": 370,
      "category": "wallet"
    },
    "エルメス シューズ": {
      "condition_excellent": 45000,
      "condition_good": 22000,
      "shipping_fee_est": 850
    },
    "フルラ バッグ": {
      "category": "bag",
      "condition_excellent": 14000,
      "condition_good": 7500,
      "shipping_fee_est": 850
    },
    "オールドコーチ": {
      "category": "bag",
      "condition_excellent": 18000,
      "condition_good": 9500,
      "shipping_fee_est": 850
    },
    "ゲンテン カットワーク": {
      "category": "bag",
      "condition_excellent": 25000,
      "condition_good": 12000,
      "shipping_fee_est": 850
    },
    "坂本これくしょん": {
      "category": "bag",
      "condition_excellent": 15000,
      "condition_good": 9000,
      "shipping_fee_est": 850
    },
    "コーチ 財布": {
      "category": "wallet",
      "condition_excellent": 8000,
      "condition_good": 4000,
      "shipping_fee_est": 370
    },
    "ポールスミス 財布": {
      "category": "wallet",
      "condition_excellent": 12000,
      "condition_good": 6000,
      "shipping_fee_est": 370
    },
    "マイケルコース バッグ": {
      "category": "bag",
      "condition_excellent": 12000,
      "condition_good": 6000,
      "shipping_fee_est": 850
    },
    "ケイトスペード バッグ": {
      "category": "bag",
      "condition_excellent": 10000,
      "condition_good": 5000,
      "shipping_fee_est": 850
    },
    "トリーバーチ バッグ": {
      "category": "bag",
      "condition_excellent": 18000,
      "condition_good": 9500,
      "shipping_fee_est": 850
    },
    "マークジェイコブス バッグ": {
      "category": "bag",
      "condition_excellent": 15000,
      "condition_good": 8000,
      "shipping_fee_est": 850
    },
    "アニエスベー がま口": {
      "category": "wallet",
      "condition_excellent": 9500,
      "condition_good": 5000,
      "shipping_fee_est": 370
    },
    "シャネル サンダル パンプス": {
      "category": "shoes_ladies",
      "condition_excellent": 48000,
      "condition_good": 25000,
      "shipping_fee_est": 850
    },
    "エルメス シューズ サンダル": {
      "category": "shoes_ladies",
      "condition_excellent": 55000,
      "condition_good": 28000,
      "shipping_fee_est": 850
    },
    "ルイヴィトン スニーカー サンダル": {
      "category": "shoes_ladies",
      "condition_excellent": 65000,
      "condition_good": 32000,
      "shipping_fee_est": 850
    },
    "グッチ スニーカー シューズ": {
      "category": "shoes_ladies",
      "condition_excellent": 42000,
      "condition_good": 20000,
      "shipping_fee_est": 850
    },
    "フェラガモ パンプス シューズ": {
      "category": "shoes_ladies",
      "condition_excellent": 15000,
      "condition_good": 8000,
      "shipping_fee_est": 850
    },
    "ダイアナ パンプス ブーツ": {
      "category": "shoes_ladies",
      "condition_excellent": 8000,
      "condition_good": 4000,
      "shipping_fee_est": 850
    },
    "プラダ スニーカー シューズ": {
      "category": "shoes_ladies",
      "condition_excellent": 55000,
      "condition_good": 28000,
      "shipping_fee_est": 850
    },
    "ディオール スニーカー シューズ": {
      "category": "shoes_ladies",
      "condition_excellent": 70000,
      "condition_good": 35000,
      "shipping_fee_est": 850
    },
    "ボッテガヴェネタ シューズ": {
      "category": "shoes_ladies",
      "condition_excellent": 60000,
      "condition_good": 30000,
      "shipping_fee_est": 850
    },
    "クリスチャンルブタン シューズ": {
      "category": "shoes_ladies",
      "condition_excellent": 65000,
      "condition_good": 32000,
      "shipping_fee_est": 850
    },
    "ロエベ シューズ": {
      "category": "shoes_ladies",
      "condition_excellent": 55000,
      "condition_good": 28000,
      "shipping_fee_est": 850
    },
    "サンローラン シューズ": {
      "category": "shoes_ladies",
      "condition_excellent": 50000,
      "condition_good": 25000,
      "shipping_fee_est": 850
    },
    "ミュウミュウ シューズ": {
      "category": "shoes_ladies",
      "condition_excellent": 45000,
      "condition_good": 22000,
      "shipping_fee_est": 850
    },
    "セリーヌ シューズ": {
      "category": "shoes_ladies",
      "condition_excellent": 48000,
      "condition_good": 24000,
      "shipping_fee_est": 850
    },
    "バレンシアガ スニーカー": {
      "category": "shoes_ladies",
      "condition_excellent": 52000,
      "condition_good": 26000,
      "shipping_fee_est": 850
    },
    "ペリーコ シューズ": {
      "category": "shoes_ladies",
      "condition_excellent": 12000,
      "condition_good": 6000,
      "shipping_fee_est": 850
    },
    "リーガル ローファー ビジネス": {
      "category": "shoes_mens",
      "condition_excellent": 12000,
      "condition_good": 6500,
      "shipping_fee_est": 850
    },
    "ドクターマーチン ブーツ 3ホール": {
      "category": "shoes_mens",
      "condition_excellent": 14000,
      "condition_good": 7500,
      "shipping_fee_est": 850
    },
    "レッドウィング ブーツ": {
      "category": "shoes_mens",
      "condition_excellent": 28000,
      "condition_good": 15000,
      "shipping_fee_est": 850
    },
    "コールハーン シューズ": {
      "category": "shoes_mens",
      "condition_excellent": 15000,
      "condition_good": 8000,
      "shipping_fee_est": 850
    },
    "ティンバーランド ブーツ": {
      "category": "shoes_mens",
      "condition_excellent": 12000,
      "condition_good": 6500,
      "shipping_fee_est": 850
    },
    "ナイキ スニーカー": {
      "category": "shoes_mens",
      "condition_excellent": 10000,
      "condition_good": 5500,
      "shipping_fee_est": 850
    },
    "アディダス スニーカー": {
      "category": "shoes_mens",
      "condition_excellent": 9000,
      "condition_good": 5000,
      "shipping_fee_est": 850
    },
    "ニューバランス スニーカー": {
      "category": "shoes_mens",
      "condition_excellent": 10000,
      "condition_good": 5500,
      "shipping_fee_est": 850
    },
    "ペリーコ シューズ パンプス": {
      "category": "shoes_ladies",
      "condition_excellent": 12000,
      "condition_good": 6000,
      "shipping_fee_est": 850
    },
    "ドルチェガッバーナ シューズ": {
      "category": "shoes_ladies",
      "condition_excellent": 20000,
      "condition_good": 10000,
      "shipping_fee_est": 850
    },
    "マイケルコース シューズ": {
      "category": "shoes_ladies",
      "condition_excellent": 10000,
      "condition_good": 5000,
      "shipping_fee_est": 850
    },
    "コンバース スニーカー": {
      "category": "shoes_mens",
      "condition_excellent": 8000,
      "condition_good": 4500,
      "shipping_fee_est": 850
    }
  },
  "last_update": "2026年06月07日 01:08",
  "latest_results": [
    {
      "title": "ディオール・オム 18AW テクニカルニット ローカット スニーカー 3SN232YAE ボルドー 41【中古】",
      "url": "https://auctions.yahoo.co.jp/jp/auction/d1227817930",
      "price_formatted": "24,200円",
      "profit_formatted": "36,950円",
      "expected_profit": 36950,
      "stars": "★★★★★",
      "condition": "未使用に近い",
      "remaining_time": "11時間",
      "img_url": "https://auc-pctr.c.yimg.jp/i/auctions.c.yimg.jp/images.auctions.yahoo.co.jp/image/dr000/auc0204/user/6c9ee05d5f67b9f1efa9e2ac31d90f84e6a8052ae23161e944d762d98eff29ef/i-img1200x1200-17771092207112dczjsj418180.jpg?pri=l&w=300&h=300&up=0&nf_src=sy&nf_path=images/auc/pc/top/image/1.0.3/na_170x170.png&nf_st=200",
      "target_m_price": "70,000円",
      "time_m": 660,
      "needs_photo_check": false,
      "is_white_sneaker": false,
      "needs_sole_warning": false,
      "keyword": "ディオール スニーカー シューズ"
    },
    {
      "title": "Christian Louboutin / クリスチャンルブタン | MILADY 45 FLANNEL オープントゥ リボン パンプス | 37 1/2 | グレー | レディース",
      "url": "https://auctions.yahoo.co.jp/jp/auction/1159925457",
      "price_formatted": "20,790円",
      "profit_formatted": "35,860円",
      "expected_profit": 35860,
      "stars": "★★★★★",
      "condition": "未使用に近い",
      "remaining_time": "3時間",
      "img_url": "https://auc-pctr.c.yimg.jp/i/auctions.c.yimg.jp/images.auctions.yahoo.co.jp/image/dr000/auc0511/user/3e28230cf31c7dcb42f5a34eb3441bad1f1270e37038cef0bee276e6a8027723/i-img800x800-173082175384405wk3ip73723.jpg?pri=l&w=300&h=300&up=0&nf_src=sy&nf_path=images/auc/pc/top/image/1.0.3/na_170x170.png&nf_st=200",
      "target_m_price": "65,000円",
      "time_m": 180,
      "needs_photo_check": false,
      "is_white_sneaker": false,
      "needs_sole_warning": false,
      "keyword": "クリスチャンルブタン シューズ"
    },
    {
      "title": "CELINE / セリーヌ | ウェッジソール アンクルストラップ サンダル | ベージュ | レディース",
      "url": "https://auctions.yahoo.co.jp/jp/auction/d1142108039",
      "price_formatted": "6,930円",
      "profit_formatted": "34,420円",
      "expected_profit": 34420,
      "stars": "★★★★★",
      "condition": "未使用に近い",
      "remaining_time": "3時間",
      "img_url": "https://auc-pctr.c.yimg.jp/i/auctions.c.yimg.jp/images.auctions.yahoo.co.jp/image/dr000/auc0506/users/fd090459bcbcb464e5c848014be0b1ee1895b1ed/i-img800x800-1719376099sgiqo4156993.jpg?pri=l&w=300&h=300&up=0&nf_src=sy&nf_path=images/auc/pc/top/image/1.0.3/na_170x170.png&nf_st=200",
      "target_m_price": "48,000円",
      "time_m": 180,
      "needs_photo_check": false,
      "is_white_sneaker": false,
      "needs_sole_warning": false,
      "keyword": "セリーヌ シューズ"
    },
    {
      "title": "CELINE / セリーヌ | フィービー期 スエード レザー ストラップ サンダル | 36 1/2 | ブラック | レディース",
      "url": "https://auctions.yahoo.co.jp/jp/auction/g1185572671",
      "price_formatted": "9,933円",
      "profit_formatted": "31,417円",
      "expected_profit": 31417,
      "stars": "★★★★★",
      "condition": "未使用に近い",
      "remaining_time": "2時間",
      "img_url": "https://auc-pctr.c.yimg.jp/i/auctions.c.yimg.jp/images.auctions.yahoo.co.jp/image/dr000/auc0105/user/3e28230cf31c7dcb42f5a34eb3441bad1f1270e37038cef0bee276e6a8027723/i-img800x800-1747709358842415lnqs5558.jpg?pri=l&w=300&h=300&up=0&nf_src=sy&nf_path=images/auc/pc/top/image/1.0.3/na_170x170.png&nf_st=200",
      "target_m_price": "48,000円",
      "time_m": 120,
      "needs_photo_check": false,
      "is_white_sneaker": false,
      "needs_sole_warning": false,
      "keyword": "セリーヌ シューズ"
    },
    {
      "title": "BOTTEGA VENETA / ボッテガヴェネタ スクエアトゥ アーモンド ヒールパンプス",
      "url": "https://auctions.yahoo.co.jp/jp/auction/p1193717505",
      "price_formatted": "23,100円",
      "profit_formatted": "29,050円",
      "expected_profit": 29050,
      "stars": "★★★★★",
      "condition": "未使用に近い",
      "remaining_time": "8時間",
      "img_url": "https://auc-pctr.c.yimg.jp/i/auctions.c.yimg.jp/images.auctions.yahoo.co.jp/image/dr000/auc0107/user/3e28230cf31c7dcb42f5a34eb3441bad1f1270e37038cef0bee276e6a8027723/i-img1200x1200-17532428888607c3djdu10458.jpg?pri=l&w=300&h=300&up=0&nf_src=sy&nf_path=images/auc/pc/top/image/1.0.3/na_170x170.png&nf_st=200",
      "target_m_price": "60,000円",
      "time_m": 480,
      "needs_photo_check": false,
      "is_white_sneaker": false,
      "needs_sole_warning": false,
      "keyword": "ボッテガヴェネタ シューズ"
    },
    {
      "title": "BOTTEGA VENETA◆スリッポン/34.5/ベージュ/レオパレード",
      "url": "https://auctions.yahoo.co.jp/jp/auction/x1155796793",
      "price_formatted": "3,300円",
      "profit_formatted": "21,850円",
      "expected_profit": 21850,
      "stars": "★★★★★",
      "condition": "やや傷や汚れあり",
      "remaining_time": "10分21秒",
      "img_url": "https://auc-pctr.c.yimg.jp/i/auctions.c.yimg.jp/images.auctions.yahoo.co.jp/image/dr000/auc0510/user/3641761cb5965ae1c25e46fef128dc48024c74d917fbbba78300a82a1ccb4cff/i-img900x1200-17282025348535ggjdyr107753.jpg?pri=l&w=300&h=300&up=0&nf_src=sy&nf_path=images/auc/pc/top/image/1.0.3/na_170x170.png&nf_st=200",
      "target_m_price": "30,000円",
      "time_m": 10,
      "needs_photo_check": true,
      "is_white_sneaker": false,
      "needs_sole_warning": false,
      "keyword": "ボッテガヴェネタ シューズ"
    },
    {
      "title": "ボッテガヴェネタ BOTTEGA VENETA イントレチャート ハイカットスニーカー シューズ 白 ホワイト IBO96 メンズ",
      "url": "https://auctions.yahoo.co.jp/jp/auction/j1230953891",
      "price_formatted": "7,800円",
      "profit_formatted": "20,050円",
      "expected_profit": 20050,
      "stars": "★★★★★",
      "condition": "やや傷や汚れあり",
      "remaining_time": "5時間",
      "img_url": "https://auc-pctr.c.yimg.jp/i/auctions.c.yimg.jp/images.auctions.yahoo.co.jp/image/dr000/auc0205/user/1a5ffb9ea9b949dff605eef2dc10bfee6dd43115da2aeab12bda98ae99737110/i-img1024x1024-17795471331273uosikz496.jpg?pri=l&w=300&h=300&up=0&nf_src=sy&nf_path=images/auc/pc/top/image/1.0.3/na_170x170.png&nf_st=200",
      "target_m_price": "33,000円",
      "time_m": 300,
      "needs_photo_check": true,
      "is_white_sneaker": true,
      "needs_sole_warning": false,
      "keyword": "ボッテガヴェネタ シューズ"
    },
    {
      "title": "PRADA SPORT◆ローカットスニーカー/-/RED/E2003",
      "url": "https://auctions.yahoo.co.jp/jp/auction/b1216348248",
      "price_formatted": "5,060円",
      "profit_formatted": "18,290円",
      "expected_profit": 18290,
      "stars": "★★★★★",
      "condition": "やや傷や汚れあり",
      "remaining_time": "9時間",
      "img_url": "https://auc-pctr.c.yimg.jp/i/auctions.c.yimg.jp/images.auctions.yahoo.co.jp/image/dr000/auc0201/user/3641761cb5965ae1c25e46fef128dc48024c74d917fbbba78300a82a1ccb4cff/i-img900x1200-17686919359458fzfs4v32870.jpg?pri=l&w=300&h=300&up=0&nf_src=sy&nf_path=images/auc/pc/top/image/1.0.3/na_170x170.png&nf_st=200",
      "target_m_price": "28,000円",
      "time_m": 540,
      "needs_photo_check": true,
      "is_white_sneaker": false,
      "needs_sole_warning": false,
      "keyword": "プラダ スニーカー シューズ"
    },
    {
      "title": "YVES SAINT LAURENT◆パンプス/34.5",
      "url": "https://auctions.yahoo.co.jp/jp/auction/w1196690919",
      "price_formatted": "2,860円",
      "profit_formatted": "17,790円",
      "expected_profit": 17790,
      "stars": "★★★★★",
      "condition": "やや傷や汚れあり",
      "remaining_time": "7時間",
      "img_url": "https://auc-pctr.c.yimg.jp/i/auctions.c.yimg.jp/images.auctions.yahoo.co.jp/image/dr000/auc0108/user/3641761cb5965ae1c25e46fef128dc48024c74d917fbbba78300a82a1ccb4cff/i-img900x1200-17554679822309xmj9uz76767.jpg?pri=l&w=300&h=300&up=0&nf_src=sy&nf_path=images/auc/pc/top/image/1.0.3/na_170x170.png&nf_st=200",
      "target_m_price": "25,000円",
      "time_m": 420,
      "needs_photo_check": true,
      "is_white_sneaker": false,
      "needs_sole_warning": false,
      "keyword": "サンローラン シューズ"
    },
    {
      "title": "LOEWE◆パンプス/36/BRW/スウェード",
      "url": "https://auctions.yahoo.co.jp/jp/auction/u1178327789",
      "price_formatted": "6,160円",
      "profit_formatted": "17,190円",
      "expected_profit": 17190,
      "stars": "★★★★★",
      "condition": "やや傷や汚れあり",
      "remaining_time": "11時間",
      "img_url": "https://auc-pctr.c.yimg.jp/i/auctions.c.yimg.jp/images.auctions.yahoo.co.jp/image/dr000/auc0103/user/3641761cb5965ae1c25e46fef128dc48024c74d917fbbba78300a82a1ccb4cff/i-img900x1200-17428532789373zwqaxs27.jpg?pri=l&w=300&h=300&up=0&nf_src=sy&nf_path=images/auc/pc/top/image/1.0.3/na_170x170.png&nf_st=200",
      "target_m_price": "28,000円",
      "time_m": 660,
      "needs_photo_check": true,
      "is_white_sneaker": false,
      "needs_sole_warning": false,
      "keyword": "ロエベ シューズ"
    },
    {
      "title": "R4904R40　▼Christian Louboutin クリスチャンルブタン▼　スタッズ付き ウール スリッポン シューズ グレー 36.5/23.5cm パンプス",
      "url": "https://auctions.yahoo.co.jp/jp/auction/n1220808580",
      "price_formatted": "9,900円",
      "profit_formatted": "17,050円",
      "expected_profit": 17050,
      "stars": "★★★★★",
      "condition": "やや傷や汚れあり / サイズ: 23.5cm (L判OK)",
      "remaining_time": "38分7秒",
      "img_url": "https://auc-pctr.c.yimg.jp/i/auctions.c.yimg.jp/images.auctions.yahoo.co.jp/image/dr000/auc0202/user/135a3eb2e71b08eae8d8d189bad75942ffc0d51ca7cf0ba68b19a3e36f24edd7/i-img960x960-17719532717830ozi1p49560.jpg?pri=l&w=300&h=300&up=0&nf_src=sy&nf_path=images/auc/pc/top/image/1.0.3/na_170x170.png&nf_st=200",
      "target_m_price": "32,000円",
      "time_m": 38,
      "needs_photo_check": true,
      "is_white_sneaker": false,
      "needs_sole_warning": false,
      "keyword": "クリスチャンルブタン シューズ"
    },
    {
      "title": "Dior HOMME◆ローカットスニーカー/39/BLK/18EDC/Beeプリント",
      "url": "https://auctions.yahoo.co.jp/jp/auction/p1187694738",
      "price_formatted": "12,760円",
      "profit_formatted": "16,890円",
      "expected_profit": 16890,
      "stars": "★★★★★",
      "condition": "やや傷や汚れあり",
      "remaining_time": "5時間",
      "img_url": "https://auc-pctr.c.yimg.jp/i/auctions.c.yimg.jp/images.auctions.yahoo.co.jp/image/dr000/auc0106/user/3641761cb5965ae1c25e46fef128dc48024c74d917fbbba78300a82a1ccb4cff/i-img900x1200-17491560119532gpfzpd12131.jpg?pri=l&w=300&h=300&up=0&nf_src=sy&nf_path=images/auc/pc/top/image/1.0.3/na_170x170.png&nf_st=200",
      "target_m_price": "35,000円",
      "time_m": 300,
      "needs_photo_check": true,
      "is_white_sneaker": false,
      "needs_sole_warning": false,
      "keyword": "ディオール スニーカー シューズ"
    },
    {
      "title": "YVES SAINT LAURENT◆パンプス/34.5/BLK/レザー",
      "url": "https://auctions.yahoo.co.jp/jp/auction/q1216485513",
      "price_formatted": "3,960円",
      "profit_formatted": "16,690円",
      "expected_profit": 16690,
      "stars": "★★★★★",
      "condition": "やや傷や汚れあり",
      "remaining_time": "2時間",
      "img_url": "https://auc-pctr.c.yimg.jp/i/auctions.c.yimg.jp/images.auctions.yahoo.co.jp/image/dr000/auc0201/user/3641761cb5965ae1c25e46fef128dc48024c74d917fbbba78300a82a1ccb4cff/i-img900x1200-17687844446885r6cs8p78600.jpg?pri=l&w=300&h=300&up=0&nf_src=sy&nf_path=images/auc/pc/top/image/1.0.3/na_170x170.png&nf_st=200",
      "target_m_price": "25,000円",
      "time_m": 120,
      "needs_photo_check": true,
      "is_white_sneaker": false,
      "needs_sole_warning": false,
      "keyword": "サンローラン シューズ"
    },
    {
      "title": "YVES SAINT LAURENT◆パンプス/36/NVY",
      "url": "https://auctions.yahoo.co.jp/jp/auction/m1204851119",
      "price_formatted": "3,960円",
      "profit_formatted": "16,690円",
      "expected_profit": 16690,
      "stars": "★★★★★",
      "condition": "やや傷や汚れあり",
      "remaining_time": "6時間",
      "img_url": "https://auc-pctr.c.yimg.jp/i/auctions.c.yimg.jp/images.auctions.yahoo.co.jp/image/dr000/auc0110/user/3641761cb5965ae1c25e46fef128dc48024c74d917fbbba78300a82a1ccb4cff/i-img900x1200-17610938049015f1nriq19504.jpg?pri=l&w=300&h=300&up=0&nf_src=sy&nf_path=images/auc/pc/top/image/1.0.3/na_170x170.png&nf_st=200",
      "target_m_price": "25,000円",
      "time_m": 360,
      "needs_photo_check": true,
      "is_white_sneaker": false,
      "needs_sole_warning": false,
      "keyword": "サンローラン シューズ"
    },
    {
      "title": "PRADA SPORT◆ローカットスニーカー/39/KHK/エナメル/3E4897",
      "url": "https://auctions.yahoo.co.jp/jp/auction/1206496106",
      "price_formatted": "7,260円",
      "profit_formatted": "16,090円",
      "expected_profit": 16090,
      "stars": "★★★★★",
      "condition": "やや傷や汚れあり",
      "remaining_time": "9時間",
      "img_url": "https://auc-pctr.c.yimg.jp/i/auctions.c.yimg.jp/images.auctions.yahoo.co.jp/image/dr000/auc0111/user/3641761cb5965ae1c25e46fef128dc48024c74d917fbbba78300a82a1ccb4cff/i-img900x1200-17622179149402sellug40779.jpg?pri=l&w=300&h=300&up=0&nf_src=sy&nf_path=images/auc/pc/top/image/1.0.3/na_170x170.png&nf_st=200",
      "target_m_price": "28,000円",
      "time_m": 540,
      "needs_photo_check": true,
      "is_white_sneaker": false,
      "needs_sole_warning": false,
      "keyword": "プラダ スニーカー シューズ"
    },
    {
      "title": "YVES SAINT LAURENT◆パンプス/35.5/BRW/レザー",
      "url": "https://auctions.yahoo.co.jp/jp/auction/j1212342151",
      "price_formatted": "5,060円",
      "profit_formatted": "15,590円",
      "expected_profit": 15590,
      "stars": "★★★★★",
      "condition": "やや傷や汚れあり",
      "remaining_time": "21分38秒",
      "img_url": "https://auc-pctr.c.yimg.jp/i/auctions.c.yimg.jp/images.auctions.yahoo.co.jp/image/dr000/auc0112/user/3641761cb5965ae1c25e46fef128dc48024c74d917fbbba78300a82a1ccb4cff/i-img900x1200-176566803413391vesek1919.jpg?pri=l&w=300&h=300&up=0&nf_src=sy&nf_path=images/auc/pc/top/image/1.0.3/na_170x170.png&nf_st=200",
      "target_m_price": "25,000円",
      "time_m": 21,
      "needs_photo_check": true,
      "is_white_sneaker": false,
      "needs_sole_warning": false,
      "keyword": "サンローラン シューズ"
    },
    {
      "title": "YVES SAINT LAURENT◆パンプス/37/ベージュ",
      "url": "https://auctions.yahoo.co.jp/jp/auction/g1222961697",
      "price_formatted": "5,060円",
      "profit_formatted": "15,590円",
      "expected_profit": 15590,
      "stars": "★★★★★",
      "condition": "やや傷や汚れあり",
      "remaining_time": "2時間",
      "img_url": "https://auc-pctr.c.yimg.jp/i/auctions.c.yimg.jp/images.auctions.yahoo.co.jp/image/dr000/auc0203/user/3641761cb5965ae1c25e46fef128dc48024c74d917fbbba78300a82a1ccb4cff/i-img900x1200-177352791480497utdjx365.jpg?pri=l&w=300&h=300&up=0&nf_src=sy&nf_path=images/auc/pc/top/image/1.0.3/na_170x170.png&nf_st=200",
      "target_m_price": "25,000円",
      "time_m": 120,
      "needs_photo_check": true,
      "is_white_sneaker": false,
      "needs_sole_warning": false,
      "keyword": "サンローラン シューズ"
    },
    {
      "title": "YVES SAINT LAURENT◆パンプス/36.5",
      "url": "https://auctions.yahoo.co.jp/jp/auction/r1196585067",
      "price_formatted": "5,060円",
      "profit_formatted": "15,590円",
      "expected_profit": 15590,
      "stars": "★★★★★",
      "condition": "やや傷や汚れあり",
      "remaining_time": "5時間",
      "img_url": "https://auc-pctr.c.yimg.jp/i/auctions.c.yimg.jp/images.auctions.yahoo.co.jp/image/dr000/auc0108/user/3641761cb5965ae1c25e46fef128dc48024c74d917fbbba78300a82a1ccb4cff/i-img900x1200-17553830376351ltwl5i6926.jpg?pri=l&w=300&h=300&up=0&nf_src=sy&nf_path=images/auc/pc/top/image/1.0.3/na_170x170.png&nf_st=200",
      "target_m_price": "25,000円",
      "time_m": 300,
      "needs_photo_check": true,
      "is_white_sneaker": false,
      "needs_sole_warning": false,
      "keyword": "サンローラン シューズ"
    },
    {
      "title": "YVES SAINT LAURENT◆シューズ/35.5/PUP",
      "url": "https://auctions.yahoo.co.jp/jp/auction/h1195857345",
      "price_formatted": "5,060円",
      "profit_formatted": "15,590円",
      "expected_profit": 15590,
      "stars": "★★★★★",
      "condition": "やや傷や汚れあり",
      "remaining_time": "8時間",
      "img_url": "https://auc-pctr.c.yimg.jp/i/auctions.c.yimg.jp/images.auctions.yahoo.co.jp/image/dr000/auc0108/user/3641761cb5965ae1c25e46fef128dc48024c74d917fbbba78300a82a1ccb4cff/i-img900x1200-17547813203158hdj1gd719.jpg?pri=l&w=300&h=300&up=0&nf_src=sy&nf_path=images/auc/pc/top/image/1.0.3/na_170x170.png&nf_st=200",
      "target_m_price": "25,000円",
      "time_m": 480,
      "needs_photo_check": true,
      "is_white_sneaker": false,
      "needs_sole_warning": false,
      "keyword": "サンローラン シューズ"
    },
    {
      "title": "YVES SAINT LAURENT◆シューズ/35.5/BLK",
      "url": "https://auctions.yahoo.co.jp/jp/auction/c1195854984",
      "price_formatted": "5,060円",
      "profit_formatted": "15,590円",
      "expected_profit": 15590,
      "stars": "★★★★★",
      "condition": "やや傷や汚れあり",
      "remaining_time": "8時間",
      "img_url": "https://auc-pctr.c.yimg.jp/i/auctions.c.yimg.jp/images.auctions.yahoo.co.jp/image/dr000/auc0108/user/3641761cb5965ae1c25e46fef128dc48024c74d917fbbba78300a82a1ccb4cff/i-img900x1200-175478895741375fmuyh38312.jpg?pri=l&w=300&h=300&up=0&nf_src=sy&nf_path=images/auc/pc/top/image/1.0.3/na_170x170.png&nf_st=200",
      "target_m_price": "25,000円",
      "time_m": 480,
      "needs_photo_check": true,
      "is_white_sneaker": false,
      "needs_sole_warning": false,
      "keyword": "サンローラン シューズ"
    },
    {
      "title": "Christian Louboutin◆サンダル/35/PNK",
      "url": "https://auctions.yahoo.co.jp/jp/auction/o1220488684",
      "price_formatted": "11,660円",
      "profit_formatted": "15,290円",
      "expected_profit": 15290,
      "stars": "★★★★★",
      "condition": "やや傷や汚れあり",
      "remaining_time": "4時間",
      "img_url": "https://auc-pctr.c.yimg.jp/i/auctions.c.yimg.jp/images.auctions.yahoo.co.jp/image/dr000/auc0202/user/3641761cb5965ae1c25e46fef128dc48024c74d917fbbba78300a82a1ccb4cff/i-img900x1200-17717101069306dl4s8c36.jpg?pri=l&w=300&h=300&up=0&nf_src=sy&nf_path=images/auc/pc/top/image/1.0.3/na_170x170.png&nf_st=200",
      "target_m_price": "32,000円",
      "time_m": 240,
      "needs_photo_check": true,
      "is_white_sneaker": false,
      "needs_sole_warning": false,
      "keyword": "クリスチャンルブタン シューズ"
    },
    {
      "title": "PRADA◆ローカットスニーカー/37/GRY/スウェード",
      "url": "https://auctions.yahoo.co.jp/jp/auction/c1221680088",
      "price_formatted": "8,360円",
      "profit_formatted": "14,990円",
      "expected_profit": 14990,
      "stars": "★★★★★",
      "condition": "やや傷や汚れあり",
      "remaining_time": "2分32秒",
      "img_url": "https://auc-pctr.c.yimg.jp/i/auctions.c.yimg.jp/images.auctions.yahoo.co.jp/image/dr000/auc0203/user/3641761cb5965ae1c25e46fef128dc48024c74d917fbbba78300a82a1ccb4cff/i-img900x1200-17725861989331xfkyah210612.jpg?pri=l&w=300&h=300&up=0&nf_src=sy&nf_path=images/auc/pc/top/image/1.0.3/na_170x170.png&nf_st=200",
      "target_m_price": "28,000円",
      "time_m": 2,
      "needs_photo_check": true,
      "is_white_sneaker": false,
      "needs_sole_warning": false,
      "keyword": "プラダ スニーカー シューズ"
    },
    {
      "title": "BOTTEGA VENETA◆ローカットスニーカー/36.5/BLK",
      "url": "https://auctions.yahoo.co.jp/jp/auction/q1219660671",
      "price_formatted": "10,560円",
      "profit_formatted": "14,590円",
      "expected_profit": 14590,
      "stars": "★★★★★",
      "condition": "やや傷や汚れあり",
      "remaining_time": "2時間",
      "img_url": "https://auc-pctr.c.yimg.jp/i/auctions.c.yimg.jp/images.auctions.yahoo.co.jp/image/dr000/auc0202/user/3641761cb5965ae1c25e46fef128dc48024c74d917fbbba78300a82a1ccb4cff/i-img900x1200-177111366084668ty7kw33.jpg?pri=l&w=300&h=300&up=0&nf_src=sy&nf_path=images/auc/pc/top/image/1.0.3/na_170x170.png&nf_st=200",
      "target_m_price": "30,000円",
      "time_m": 120,
      "needs_photo_check": true,
      "is_white_sneaker": false,
      "needs_sole_warning": false,
      "keyword": "ボッテガヴェネタ シューズ"
    },
    {
      "title": "MIU MIU◆サンダル/37.5/BRW",
      "url": "https://auctions.yahoo.co.jp/jp/auction/g1199593849",
      "price_formatted": "4,400円",
      "profit_formatted": "13,550円",
      "expected_profit": 13550,
      "stars": "★★★★★",
      "condition": "やや傷や汚れあり",
      "remaining_time": "38分53秒",
      "img_url": "https://auc-pctr.c.yimg.jp/i/auctions.c.yimg.jp/images.auctions.yahoo.co.jp/image/dr000/auc0109/user/3641761cb5965ae1c25e46fef128dc48024c74d917fbbba78300a82a1ccb4cff/i-img900x1200-17574638682522bjflpk61975.jpg?pri=l&w=300&h=300&up=0&nf_src=sy&nf_path=images/auc/pc/top/image/1.0.3/na_170x170.png&nf_st=200",
      "target_m_price": "22,000円",
      "time_m": 38,
      "needs_photo_check": true,
      "is_white_sneaker": false,
      "needs_sole_warning": false,
      "keyword": "ミュウミュウ シューズ"
    },
    {
      "title": "【値下】美品 ルイヴィトン LV タティック・ライン モノグラムフラワー レザー スリッポン スニーカー サンダル サイズ9 46886",
      "url": "https://auctions.yahoo.co.jp/jp/auction/d1211112882",
      "price_formatted": "44,000円",
      "profit_formatted": "12,650円",
      "expected_profit": 12650,
      "stars": "★★★★★",
      "condition": "未使用に近い",
      "remaining_time": "22時間",
      "img_url": "https://auc-pctr.c.yimg.jp/i/auctions.c.yimg.jp/images.auctions.yahoo.co.jp/image/dr000/auc0112/user/7e402c0a2ff036f8ea970e4569313ec78ddd29b6821ce6e9c734a7f73df7344c/i-img1200x1200-17648160316966doe1oe251474.jpg?pri=l&w=300&h=300&up=0&nf_src=sy&nf_path=images/auc/pc/top/image/1.0.3/na_170x170.png&nf_st=200",
      "target_m_price": "65,000円",
      "time_m": 1320,
      "needs_photo_check": false,
      "is_white_sneaker": false,
      "needs_sole_warning": false,
      "keyword": "ルイヴィトン スニーカー サンダル"
    },
    {
      "title": "良品 LOEWE ロエベ アナグラム フラップ キャンバス スニーカー 822201 37 23.5cm相当 ブラック",
      "url": "https://auctions.yahoo.co.jp/jp/auction/m1213232353",
      "price_formatted": "11,000円",
      "profit_formatted": "12,350円",
      "expected_profit": 12350,
      "stars": "★★★★★",
      "condition": "やや傷や汚れあり / サイズ: 23.5cm (L判OK)",
      "remaining_time": "21時間",
      "img_url": "https://auc-pctr.c.yimg.jp/i/auctions.c.yimg.jp/images.auctions.yahoo.co.jp/image/dr000/auc0112/user/d61e2f5594fd7794a0a591973524f9c543851a1869f0ff72248d8453d7a420e6/i-img1000x1000-17663159841112nfkmiw209.jpg?pri=l&w=300&h=300&up=0&nf_src=sy&nf_path=images/auc/pc/top/image/1.0.3/na_170x170.png&nf_st=200",
      "target_m_price": "28,000円",
      "time_m": 1260,
      "needs_photo_check": true,
      "is_white_sneaker": false,
      "needs_sole_warning": false,
      "keyword": "ロエベ シューズ"
    },
    {
      "title": "Christian Louboutin◆パンプス/35.5/ブラック/エナメル/パテントレザー/リボン//",
      "url": "https://auctions.yahoo.co.jp/jp/auction/q1225412131",
      "price_formatted": "14,960円",
      "profit_formatted": "11,990円",
      "expected_profit": 11990,
      "stars": "★★★★★",
      "condition": "やや傷や汚れあり",
      "remaining_time": "2時間",
      "img_url": "https://auc-pctr.c.yimg.jp/i/auctions.c.yimg.jp/images.auctions.yahoo.co.jp/image/dr000/auc0204/user/3641761cb5965ae1c25e46fef128dc48024c74d917fbbba78300a82a1ccb4cff/i-img900x1200-17753563830595rupayu308.jpg?pri=l&w=300&h=300&up=0&nf_src=sy&nf_path=images/auc/pc/top/image/1.0.3/na_170x170.png&nf_st=200",
      "target_m_price": "32,000円",
      "time_m": 120,
      "needs_photo_check": true,
      "is_white_sneaker": false,
      "needs_sole_warning": false,
      "keyword": "クリスチャンルブタン シューズ"
    },
    {
      "title": "Christian Louboutin◆パンプス/34.5/BLK",
      "url": "https://auctions.yahoo.co.jp/jp/auction/s1187094242",
      "price_formatted": "14,960円",
      "profit_formatted": "11,990円",
      "expected_profit": 11990,
      "stars": "★★★★★",
      "condition": "やや傷や汚れあり",
      "remaining_time": "4時間",
      "img_url": "https://auc-pctr.c.yimg.jp/i/auctions.c.yimg.jp/images.auctions.yahoo.co.jp/image/dr000/auc0106/user/3641761cb5965ae1c25e46fef128dc48024c74d917fbbba78300a82a1ccb4cff/i-img900x1200-17487437654202kbmimr1492.jpg?pri=l&w=300&h=300&up=0&nf_src=sy&nf_path=images/auc/pc/top/image/1.0.3/na_170x170.png&nf_st=200",
      "target_m_price": "32,000円",
      "time_m": 240,
      "needs_photo_check": true,
      "is_white_sneaker": false,
      "needs_sole_warning": false,
      "keyword": "クリスチャンルブタン シューズ"
    },
    {
      "title": "HERMES◆パンプス/34.5/CML/メタリックサンダル//",
      "url": "https://auctions.yahoo.co.jp/jp/auction/m1231824314",
      "price_formatted": "11,660円",
      "profit_formatted": "11,690円",
      "expected_profit": 11690,
      "stars": "★★★★★",
      "condition": "やや傷や汚れあり",
      "remaining_time": "9時間",
      "img_url": "https://auc-pctr.c.yimg.jp/i/auctions.c.yimg.jp/images.auctions.yahoo.co.jp/image/dr000/auc0205/user/3641761cb5965ae1c25e46fef128dc48024c74d917fbbba78300a82a1ccb4cff/i-img900x1200-17801788236007vem7fq25125.jpg?pri=l&w=300&h=300&up=0&nf_src=sy&nf_path=images/auc/pc/top/image/1.0.3/na_170x170.png&nf_st=200",
      "target_m_price": "28,000円",
      "time_m": 540,
      "needs_photo_check": true,
      "is_white_sneaker": false,
      "needs_sole_warning": false,
      "keyword": "エルメス シューズ サンダル"
    },
    {
      "title": "LOEWE◆シューズ/40/BEG/スウェード",
      "url": "https://auctions.yahoo.co.jp/jp/auction/o1109369257",
      "price_formatted": "11,660円",
      "profit_formatted": "11,690円",
      "expected_profit": 11690,
      "stars": "★★★★★",
      "condition": "やや傷や汚れあり",
      "remaining_time": "2時間",
      "img_url": "https://auc-pctr.c.yimg.jp/i/auctions.c.yimg.jp/images.auctions.yahoo.co.jp/image/dr000/auc0410/users/0e7b7992c7a2872510a12dbcb0110c3b5774e212/i-img900x1200-1696884120p4twnn980864.jpg?pri=l&w=300&h=300&up=0&nf_src=sy&nf_path=images/auc/pc/top/image/1.0.3/na_170x170.png&nf_st=200",
      "target_m_price": "28,000円",
      "time_m": 120,
      "needs_photo_check": true,
      "is_white_sneaker": false,
      "needs_sole_warning": false,
      "keyword": "ロエベ シューズ"
    },
    {
      "title": "◇ COLE HAAN コール ハーン ラウンドトゥ チャンキーヒール エナメル パンプス 表記なし イエロー レディース E",
      "url": "https://auctions.yahoo.co.jp/jp/auction/j1209825469",
      "price_formatted": "468円",
      "profit_formatted": "11,182円",
      "expected_profit": 11182,
      "stars": "★★★★★",
      "condition": "未使用に近い",
      "remaining_time": "12分47秒",
      "img_url": "https://auc-pctr.c.yimg.jp/i/auctions.c.yimg.jp/images.auctions.yahoo.co.jp/image/dr000/auc0112/user/3eae7ab3e3789d02c229d8d277fb7babb824edbfa53bf14b591e86635b870530/i-img500x500-17645358735664jwofm111925.jpg?pri=l&w=300&h=300&up=0&nf_src=sy&nf_path=images/auc/pc/top/image/1.0.3/na_170x170.png&nf_st=200",
      "target_m_price": "15,000円",
      "time_m": 12,
      "needs_photo_check": false,
      "is_white_sneaker": false,
      "needs_sole_warning": false,
      "keyword": "コールハーン シューズ"
    },
    {
      "title": "CELINE / セリーヌ | クロコ型押し ショートブーツ | 34 | ホワイト | レディース",
      "url": "https://auctions.yahoo.co.jp/jp/auction/d1157540100",
      "price_formatted": "34,650円",
      "profit_formatted": "11,020円",
      "expected_profit": 11020,
      "stars": "★★★★★",
      "condition": "未使用に近い",
      "remaining_time": "5時間",
      "img_url": "https://auc-pctr.c.yimg.jp/i/auctions.c.yimg.jp/images.auctions.yahoo.co.jp/image/dr000/auc0510/user/3e28230cf31c7dcb42f5a34eb3441bad1f1270e37038cef0bee276e6a8027723/i-img800x800-17292708629293w97pbh249055.jpg?pri=l&w=300&h=300&up=0&nf_src=sy&nf_path=images/auc/pc/top/image/1.0.3/na_170x170.png&nf_st=200",
      "target_m_price": "52,800円",
      "time_m": 300,
      "needs_photo_check": false,
      "is_white_sneaker": true,
      "needs_sole_warning": false,
      "keyword": "セリーヌ シューズ"
    },
    {
      "title": "BOTTEGA VENETA◆ストラップレザーサンダル/39/BLU/レザー",
      "url": "https://auctions.yahoo.co.jp/jp/auction/f1219654224",
      "price_formatted": "14,960円",
      "profit_formatted": "10,190円",
      "expected_profit": 10190,
      "stars": "★★★★★",
      "condition": "やや傷や汚れあり",
      "remaining_time": "2時間",
      "img_url": "https://auc-pctr.c.yimg.jp/i/auctions.c.yimg.jp/images.auctions.yahoo.co.jp/image/dr000/auc0202/user/3641761cb5965ae1c25e46fef128dc48024c74d917fbbba78300a82a1ccb4cff/i-img900x1200-17711129639336xpryqk27438.jpg?pri=l&w=300&h=300&up=0&nf_src=sy&nf_path=images/auc/pc/top/image/1.0.3/na_170x170.png&nf_st=200",
      "target_m_price": "30,000円",
      "time_m": 120,
      "needs_photo_check": true,
      "is_white_sneaker": false,
      "needs_sole_warning": false,
      "keyword": "ボッテガヴェネタ シューズ"
    },
    {
      "title": "MIU MIU◆ブーツ/35.5/BLK/レザー",
      "url": "https://auctions.yahoo.co.jp/jp/auction/h1207516751",
      "price_formatted": "8,360円",
      "profit_formatted": "9,590円",
      "expected_profit": 9590,
      "stars": "★★★★★",
      "condition": "やや傷や汚れあり",
      "remaining_time": "4時間",
      "img_url": "https://auc-pctr.c.yimg.jp/i/auctions.c.yimg.jp/images.auctions.yahoo.co.jp/image/dr000/auc0111/user/3641761cb5965ae1c25e46fef128dc48024c74d917fbbba78300a82a1ccb4cff/i-img900x1200-17629064149000gtgdtm854.jpg?pri=l&w=300&h=300&up=0&nf_src=sy&nf_path=images/auc/pc/top/image/1.0.3/na_170x170.png&nf_st=200",
      "target_m_price": "22,000円",
      "time_m": 240,
      "needs_photo_check": true,
      "is_white_sneaker": false,
      "needs_sole_warning": false,
      "keyword": "ミュウミュウ シューズ"
    },
    {
      "title": "ドルチェ&ガッバーナ ヒール パンプス シューズ メッシュ ブラック ホワイト ドルガバ DOLCE&GABBANA サイズ37(約24cm)]",
      "url": "https://auctions.yahoo.co.jp/jp/auction/c1218038548",
      "price_formatted": "8,800円",
      "profit_formatted": "9,150円",
      "expected_profit": 9150,
      "stars": "★★★★★",
      "condition": "未使用に近い / サイズ: 24.0cm (L判OK)",
      "remaining_time": "3時間",
      "img_url": "https://auc-pctr.c.yimg.jp/i/auctions.c.yimg.jp/images.auctions.yahoo.co.jp/image/dr000/auc0202/user/98a295fd1911fed7844244b7ad0576743cbb7b3d842d87d186a1ef4704c46b42/i-img1000x1000-17699129158987klcpdn31914.jpg?pri=l&w=300&h=300&up=0&nf_src=sy&nf_path=images/auc/pc/top/image/1.0.3/na_170x170.png&nf_st=200",
      "target_m_price": "22,000円",
      "time_m": 180,
      "needs_photo_check": false,
      "is_white_sneaker": true,
      "needs_sole_warning": false,
      "keyword": "ドルチェガッバーナ シューズ"
    },
    {
      "title": "◇ PELLICO ペリーコ サンダル サイズ37 ブラウン系 レディース E",
      "url": "https://auctions.yahoo.co.jp/jp/auction/e1211796627",
      "price_formatted": "468円",
      "profit_formatted": "8,482円",
      "expected_profit": 8482,
      "stars": "★★★★★",
      "condition": "未使用に近い / サイズ: 23.5cm (L判OK)",
      "remaining_time": "57分17秒",
      "img_url": "https://auc-pctr.c.yimg.jp/i/auctions.c.yimg.jp/images.auctions.yahoo.co.jp/image/dr000/auc0112/user/3eae7ab3e3789d02c229d8d277fb7babb824edbfa53bf14b591e86635b870530/i-img500x500-17652818095372fg9v9x1216.jpg?pri=l&w=300&h=300&up=0&nf_src=sy&nf_path=images/auc/pc/top/image/1.0.3/na_170x170.png&nf_st=200",
      "target_m_price": "12,000円",
      "time_m": 57,
      "needs_photo_check": false,
      "is_white_sneaker": false,
      "needs_sole_warning": false,
      "keyword": "ペリーコ シューズ"
    },
    {
      "title": "◇ Θ PELLICO ペリーコ つま先装飾 ハイヒール サイズ36 ブルー系 レディース E",
      "url": "https://auctions.yahoo.co.jp/jp/auction/q1211443278",
      "price_formatted": "468円",
      "profit_formatted": "8,482円",
      "expected_profit": 8482,
      "stars": "★★★★★",
      "condition": "未使用に近い / サイズ: 22.5cm (L判OK)",
      "remaining_time": "2時間",
      "img_url": "https://auc-pctr.c.yimg.jp/i/auctions.c.yimg.jp/images.auctions.yahoo.co.jp/image/dr000/auc0112/user/3eae7ab3e3789d02c229d8d277fb7babb824edbfa53bf14b591e86635b870530/i-img500x500-17650525845343tgae3r214020.jpg?pri=l&w=300&h=300&up=0&nf_src=sy&nf_path=images/auc/pc/top/image/1.0.3/na_170x170.png&nf_st=200",
      "target_m_price": "12,000円",
      "time_m": 120,
      "needs_photo_check": false,
      "is_white_sneaker": false,
      "needs_sole_warning": false,
      "keyword": "ペリーコ シューズ"
    },
    {
      "title": "◇ Θ PELLICO ペリーコ つま先装飾 ハイヒール サイズ36 ブルー系 レディース E",
      "url": "https://auctions.yahoo.co.jp/jp/auction/q1211443278",
      "price_formatted": "468円",
      "profit_formatted": "8,482円",
      "expected_profit": 8482,
      "stars": "★★★★★",
      "condition": "未使用に近い / サイズ: 22.5cm (L判OK)",
      "remaining_time": "2時間",
      "img_url": "https://auc-pctr.c.yimg.jp/i/auctions.c.yimg.jp/images.auctions.yahoo.co.jp/image/dr000/auc0112/user/3eae7ab3e3789d02c229d8d277fb7babb824edbfa53bf14b591e86635b870530/i-img500x500-17650525845343tgae3r214020.jpg?pri=l&w=300&h=300&up=0&nf_src=sy&nf_path=images/auc/pc/top/image/1.0.3/na_170x170.png&nf_st=200",
      "target_m_price": "12,000円",
      "time_m": 120,
      "needs_photo_check": false,
      "is_white_sneaker": false,
      "needs_sole_warning": false,
      "keyword": "ペリーコ シューズ パンプス"
    },
    {
      "title": "◇ PELLICO SUNNY ペリーコサニー トング クロス サンダル パンプス サイズ37 ブラウン レディース E",
      "url": "https://auctions.yahoo.co.jp/jp/auction/g1211800609",
      "price_formatted": "468円",
      "profit_formatted": "8,482円",
      "expected_profit": 8482,
      "stars": "★★★★★",
      "condition": "未使用に近い / サイズ: 23.5cm (L判OK)",
      "remaining_time": "5時間",
      "img_url": "https://auc-pctr.c.yimg.jp/i/auctions.c.yimg.jp/images.auctions.yahoo.co.jp/image/dr000/auc0112/user/3eae7ab3e3789d02c229d8d277fb7babb824edbfa53bf14b591e86635b870530/i-img500x500-17652819779881wu80ej24183.jpg?pri=l&w=300&h=300&up=0&nf_src=sy&nf_path=images/auc/pc/top/image/1.0.3/na_170x170.png&nf_st=200",
      "target_m_price": "12,000円",
      "time_m": 300,
      "needs_photo_check": false,
      "is_white_sneaker": false,
      "needs_sole_warning": false,
      "keyword": "ペリーコ シューズ パンプス"
    },
    {
      "title": "HERMES◆サンダル/36/BRW",
      "url": "https://auctions.yahoo.co.jp/jp/auction/m1118069336",
      "price_formatted": "14,960円",
      "profit_formatted": "8,390円",
      "expected_profit": 8390,
      "stars": "★★★★★",
      "condition": "やや傷や汚れあり",
      "remaining_time": "6時間",
      "img_url": "https://auc-pctr.c.yimg.jp/i/auctions.c.yimg.jp/images.auctions.yahoo.co.jp/image/dr000/auc0412/users/0e7b7992c7a2872510a12dbcb0110c3b5774e212/i-img900x1200-1702872810yb2pi1101388.jpg?pri=l&w=300&h=300&up=0&nf_src=sy&nf_path=images/auc/pc/top/image/1.0.3/na_170x170.png&nf_st=200",
      "target_m_price": "28,000円",
      "time_m": 360,
      "needs_photo_check": true,
      "is_white_sneaker": false,
      "needs_sole_warning": false,
      "keyword": "エルメス シューズ サンダル"
    },
    {
      "title": "PRADA◆ローカットスニーカー/37/WHT/3E6411",
      "url": "https://auctions.yahoo.co.jp/jp/auction/1207112455",
      "price_formatted": "14,960円",
      "profit_formatted": "8,390円",
      "expected_profit": 8390,
      "stars": "★★★★★",
      "condition": "やや傷や汚れあり",
      "remaining_time": "4時間",
      "img_url": "https://auc-pctr.c.yimg.jp/i/auctions.c.yimg.jp/images.auctions.yahoo.co.jp/image/dr000/auc0111/user/3641761cb5965ae1c25e46fef128dc48024c74d917fbbba78300a82a1ccb4cff/i-img900x1200-17626384842086yjrrqj22423.jpg?pri=l&w=300&h=300&up=0&nf_src=sy&nf_path=images/auc/pc/top/image/1.0.3/na_170x170.png&nf_st=200",
      "target_m_price": "28,000円",
      "time_m": 240,
      "needs_photo_check": true,
      "is_white_sneaker": false,
      "needs_sole_warning": false,
      "keyword": "プラダ スニーカー シューズ"
    },
    {
      "title": "PRADA◆ローカットスニーカー/-/WHT",
      "url": "https://auctions.yahoo.co.jp/jp/auction/1230994519",
      "price_formatted": "14,960円",
      "profit_formatted": "8,390円",
      "expected_profit": 8390,
      "stars": "★★★★★",
      "condition": "やや傷や汚れあり",
      "remaining_time": "4時間",
      "img_url": "https://auc-pctr.c.yimg.jp/i/auctions.c.yimg.jp/images.auctions.yahoo.co.jp/image/dr000/auc0205/user/3641761cb5965ae1c25e46fef128dc48024c74d917fbbba78300a82a1ccb4cff/i-img900x1200-17795761558583yp9hqv2844.jpg?pri=l&w=300&h=300&up=0&nf_src=sy&nf_path=images/auc/pc/top/image/1.0.3/na_170x170.png&nf_st=200",
      "target_m_price": "28,000円",
      "time_m": 240,
      "needs_photo_check": true,
      "is_white_sneaker": false,
      "needs_sole_warning": false,
      "keyword": "プラダ スニーカー シューズ"
    },
    {
      "title": "FURLA(フルラ) Alissa アリッサ 2way ミニボストン ハンド ショルダーバッグ レディース 中古 古着 0704",
      "url": "https://auctions.yahoo.co.jp/jp/auction/c1214616337",
      "price_formatted": "2,629円",
      "profit_formatted": "8,121円",
      "expected_profit": 8121,
      "stars": "★★★★★",
      "condition": "未使用に近い / サイズ: 判定不要",
      "remaining_time": "37分57秒",
      "img_url": "https://auc-pctr.c.yimg.jp/i/auctions.c.yimg.jp/images.auctions.yahoo.co.jp/image/dr000/auc0201/user/02537f801bf6427ee25e01f2229c06376f5ae84f829d8e2dd64b405ad5a51969/i-img1200x1200-17674363157165nit13135.jpg?pri=l&w=300&h=300&up=0&nf_src=sy&nf_path=images/auc/pc/top/image/1.0.3/na_170x170.png&nf_st=200",
      "target_m_price": "14,000円",
      "time_m": 37,
      "needs_photo_check": false,
      "is_white_sneaker": false,
      "needs_sole_warning": false,
      "keyword": "フルラ バッグ"
    },
    {
      "title": "genten/ゲンテン 二つ折り財布/ウォレット カットワーク ブラウン/茶色 レザー L字ファスナー レディース[OJ02685]",
      "url": "https://auctions.yahoo.co.jp/jp/auction/v1231429799",
      "price_formatted": "856円",
      "profit_formatted": "8,094円",
      "expected_profit": 8094,
      "stars": "★★★★★",
      "condition": "やや傷や汚れあり / サイズ: 判定不要",
      "remaining_time": "8時間",
      "img_url": "https://auc-pctr.c.yimg.jp/i/auctions.c.yimg.jp/images.auctions.yahoo.co.jp/image/dr000/auc0205/user/6d230eb147fab48aa665eec42c73d2d2208f331fa26b8b751c28f777fa08ec38/i-img1200x1200-17798885029195kzyddc26.jpg?pri=l&w=300&h=300&up=0&nf_src=sy&nf_path=images/auc/pc/top/image/1.0.3/na_170x170.png&nf_st=200",
      "target_m_price": "12,000円",
      "time_m": 480,
      "needs_photo_check": true,
      "is_white_sneaker": false,
      "needs_sole_warning": false,
      "keyword": "ゲンテン カットワーク"
    },
    {
      "title": "DOLCE＆GABBANA / ドルチェ＆ガッバーナドルガバ | レース厚底サンダル | 38 | ブラック | レディース",
      "url": "https://auctions.yahoo.co.jp/jp/auction/e1184976863",
      "price_formatted": "8,085円",
      "profit_formatted": "8,065円",
      "expected_profit": 8065,
      "stars": "★★★★★",
      "condition": "未使用に近い",
      "remaining_time": "4時間",
      "img_url": "https://auc-pctr.c.yimg.jp/i/auctions.c.yimg.jp/images.auctions.yahoo.co.jp/image/dr000/auc0105/user/3e28230cf31c7dcb42f5a34eb3441bad1f1270e37038cef0bee276e6a8027723/i-img1200x1200-17472959576612yey51r109156.jpg?pri=l&w=300&h=300&up=0&nf_src=sy&nf_path=images/auc/pc/top/image/1.0.3/na_170x170.png&nf_st=200",
      "target_m_price": "20,000円",
      "time_m": 240,
      "needs_photo_check": false,
      "is_white_sneaker": false,
      "needs_sole_warning": false,
      "keyword": "ドルチェガッバーナ シューズ"
    },
    {
      "title": "P5313R40　▼miumiu ミュウミュウ▼　ベルベット ビジュー スリッポンシューズ ボルドー 38.5/24-24.5cm ゴールド刺繍 フラットシューズ",
      "url": "https://auctions.yahoo.co.jp/jp/auction/q1190216236",
      "price_formatted": "9,890円",
      "profit_formatted": "8,060円",
      "expected_profit": 8060,
      "stars": "★★★★★",
      "condition": "やや傷や汚れあり / サイズ: 24.5cm (L判OK)",
      "remaining_time": "20分53秒",
      "img_url": "https://auc-pctr.c.yimg.jp/i/auctions.c.yimg.jp/images.auctions.yahoo.co.jp/image/dr000/auc0106/user/135a3eb2e71b08eae8d8d189bad75942ffc0d51ca7cf0ba68b19a3e36f24edd7/i-img640x640-17508538744188czmlbg13882.jpg?pri=l&w=300&h=300&up=0&nf_src=sy&nf_path=images/auc/pc/top/image/1.0.3/na_170x170.png&nf_st=200",
      "target_m_price": "22,000円",
      "time_m": 20,
      "needs_photo_check": true,
      "is_white_sneaker": false,
      "needs_sole_warning": false,
      "keyword": "ミュウミュウ シューズ"
    },
    {
      "title": "BOTTEGA VENETA◆ローカットスニーカー/36.5/WHT/レザー",
      "url": "https://auctions.yahoo.co.jp/jp/auction/h1227852582",
      "price_formatted": "17,160円",
      "profit_formatted": "7,990円",
      "expected_profit": 7990,
      "stars": "★★★★★",
      "condition": "やや傷や汚れあり",
      "remaining_time": "11分11秒",
      "img_url": "https://auc-pctr.c.yimg.jp/i/auctions.c.yimg.jp/images.auctions.yahoo.co.jp/image/dr000/auc0204/user/3641761cb5965ae1c25e46fef128dc48024c74d917fbbba78300a82a1ccb4cff/i-img900x1200-17771635725957esoxy7443818.jpg?pri=l&w=300&h=300&up=0&nf_src=sy&nf_path=images/auc/pc/top/image/1.0.3/na_170x170.png&nf_st=200",
      "target_m_price": "30,000円",
      "time_m": 11,
      "needs_photo_check": true,
      "is_white_sneaker": false,
      "needs_sole_warning": false,
      "keyword": "ボッテガヴェネタ シューズ"
    },
    {
      "title": "Dior HOMME◆ハイカットスニーカー/-/WHT/B21",
      "url": "https://auctions.yahoo.co.jp/jp/auction/x1227044876",
      "price_formatted": "22,660円",
      "profit_formatted": "6,990円",
      "expected_profit": 6990,
      "stars": "★★★★★",
      "condition": "やや傷や汚れあり",
      "remaining_time": "7時間",
      "img_url": "https://auc-pctr.c.yimg.jp/i/auctions.c.yimg.jp/images.auctions.yahoo.co.jp/image/dr000/auc0204/user/3641761cb5965ae1c25e46fef128dc48024c74d917fbbba78300a82a1ccb4cff/i-img900x1200-17765554800199g175ii182854.jpg?pri=l&w=300&h=300&up=0&nf_src=sy&nf_path=images/auc/pc/top/image/1.0.3/na_170x170.png&nf_st=200",
      "target_m_price": "35,000円",
      "time_m": 420,
      "needs_photo_check": true,
      "is_white_sneaker": false,
      "needs_sole_warning": false,
      "keyword": "ディオール スニーカー シューズ"
    },
    {
      "title": "CELINE◆サンダル/35/BRW/ゴールドバックル",
      "url": "https://auctions.yahoo.co.jp/jp/auction/f1227841248",
      "price_formatted": "12,760円",
      "profit_formatted": "6,990円",
      "expected_profit": 6990,
      "stars": "★★★★★",
      "condition": "やや傷や汚れあり",
      "remaining_time": "4時間",
      "img_url": "https://auc-pctr.c.yimg.jp/i/auctions.c.yimg.jp/images.auctions.yahoo.co.jp/image/dr000/auc0204/user/3641761cb5965ae1c25e46fef128dc48024c74d917fbbba78300a82a1ccb4cff/i-img900x1200-17771572190778oqy5xx267743.jpg?pri=l&w=300&h=300&up=0&nf_src=sy&nf_path=images/auc/pc/top/image/1.0.3/na_170x170.png&nf_st=200",
      "target_m_price": "24,000円",
      "time_m": 240,
      "needs_photo_check": true,
      "is_white_sneaker": false,
      "needs_sole_warning": false,
      "keyword": "セリーヌ シューズ"
    },
    {
      "title": "BOTTEGA VENETA◆ブーツ/40/CLR",
      "url": "https://auctions.yahoo.co.jp/jp/auction/d1218525902",
      "price_formatted": "18,260円",
      "profit_formatted": "6,890円",
      "expected_profit": 6890,
      "stars": "★★★★★",
      "condition": "やや傷や汚れあり",
      "remaining_time": "5時間",
      "img_url": "https://auc-pctr.c.yimg.jp/i/auctions.c.yimg.jp/images.auctions.yahoo.co.jp/image/dr000/auc0202/user/3641761cb5965ae1c25e46fef128dc48024c74d917fbbba78300a82a1ccb4cff/i-img900x1200-17702523835843mrtjtj65689.jpg?pri=l&w=300&h=300&up=0&nf_src=sy&nf_path=images/auc/pc/top/image/1.0.3/na_170x170.png&nf_st=200",
      "target_m_price": "30,000円",
      "time_m": 300,
      "needs_photo_check": true,
      "is_white_sneaker": false,
      "needs_sole_warning": false,
      "keyword": "ボッテガヴェネタ シューズ"
    },
    {
      "title": "◇ NIKE ナイキ　889053-619 スニーカー サイズ24.5 レッド レディース E",
      "url": "https://auctions.yahoo.co.jp/jp/auction/t1209757959",
      "price_formatted": "468円",
      "profit_formatted": "6,682円",
      "expected_profit": 6682,
      "stars": "★★★★★",
      "condition": "未使用に近い",
      "remaining_time": "54秒",
      "img_url": "https://auc-pctr.c.yimg.jp/i/auctions.c.yimg.jp/images.auctions.yahoo.co.jp/image/dr000/auc0111/user/3eae7ab3e3789d02c229d8d277fb7babb824edbfa53bf14b591e86635b870530/i-img500x500-17644837718945fccc0l35.jpg?pri=l&w=300&h=300&up=0&nf_src=sy&nf_path=images/auc/pc/top/image/1.0.3/na_170x170.png&nf_st=200",
      "target_m_price": "10,000円",
      "time_m": 1,
      "needs_photo_check": false,
      "is_white_sneaker": false,
      "needs_sole_warning": false,
      "keyword": "ナイキ スニーカー"
    },
    {
      "title": "◇ adidas アディダス シューズ カジュアル 運動靴 スニーカー サイズ24 ホワイト レディース E",
      "url": "https://auctions.yahoo.co.jp/jp/auction/e1209816781",
      "price_formatted": "468円",
      "profit_formatted": "6,592円",
      "expected_profit": 6592,
      "stars": "★★★★★",
      "condition": "未使用に近い",
      "remaining_time": "5分58秒",
      "img_url": "https://auc-pctr.c.yimg.jp/i/auctions.c.yimg.jp/images.auctions.yahoo.co.jp/image/dr000/auc0112/user/3eae7ab3e3789d02c229d8d277fb7babb824edbfa53bf14b591e86635b870530/i-img500x500-17645359770231nst3ey35.jpg?pri=l&w=300&h=300&up=0&nf_src=sy&nf_path=images/auc/pc/top/image/1.0.3/na_170x170.png&nf_st=200",
      "target_m_price": "9,900円",
      "time_m": 5,
      "needs_photo_check": false,
      "is_white_sneaker": true,
      "needs_sole_warning": false,
      "keyword": "アディダス スニーカー"
    },
    {
      "title": "Christian Louboutin◆ロングブーツ/35/BLK",
      "url": "https://auctions.yahoo.co.jp/jp/auction/g1211456566",
      "price_formatted": "20,460円",
      "profit_formatted": "6,490円",
      "expected_profit": 6490,
      "stars": "★★★★★",
      "condition": "やや傷や汚れあり",
      "remaining_time": "2時間",
      "img_url": "https://auc-pctr.c.yimg.jp/i/auctions.c.yimg.jp/images.auctions.yahoo.co.jp/image/dr000/auc0112/user/3641761cb5965ae1c25e46fef128dc48024c74d917fbbba78300a82a1ccb4cff/i-img900x1200-17650672005169o4n97s34.jpg?pri=l&w=300&h=300&up=0&nf_src=sy&nf_path=images/auc/pc/top/image/1.0.3/na_170x170.png&nf_st=200",
      "target_m_price": "32,000円",
      "time_m": 120,
      "needs_photo_check": true,
      "is_white_sneaker": false,
      "needs_sole_warning": false,
      "keyword": "クリスチャンルブタン シューズ"
    },
    {
      "title": "Christian Louboutin◆KIDDO ORLATO FLAT PAT ALV/VERSION BLACK/スニーカー/40.5/ブラック",
      "url": "https://auctions.yahoo.co.jp/jp/auction/r1223478843",
      "price_formatted": "20,460円",
      "profit_formatted": "6,490円",
      "expected_profit": 6490,
      "stars": "★★★★★",
      "condition": "やや傷や汚れあり",
      "remaining_time": "2時間",
      "img_url": "https://auc-pctr.c.yimg.jp/i/auctions.c.yimg.jp/images.auctions.yahoo.co.jp/image/dr000/auc0203/user/3641761cb5965ae1c25e46fef128dc48024c74d917fbbba78300a82a1ccb4cff/i-img900x1200-17738879600414ox0863270037.jpg?pri=l&w=300&h=300&up=0&nf_src=sy&nf_path=images/auc/pc/top/image/1.0.3/na_170x170.png&nf_st=200",
      "target_m_price": "32,000円",
      "time_m": 120,
      "needs_photo_check": true,
      "is_white_sneaker": false,
      "needs_sole_warning": false,
      "keyword": "クリスチャンルブタン シューズ"
    },
    {
      "title": "Christian Louboutin◆パンプス/34.5/WHT",
      "url": "https://auctions.yahoo.co.jp/jp/auction/d1190612193",
      "price_formatted": "20,460円",
      "profit_formatted": "6,490円",
      "expected_profit": 6490,
      "stars": "★★★★★",
      "condition": "やや傷や汚れあり",
      "remaining_time": "4時間",
      "img_url": "https://auc-pctr.c.yimg.jp/i/auctions.c.yimg.jp/images.auctions.yahoo.co.jp/image/dr000/auc0106/user/3641761cb5965ae1c25e46fef128dc48024c74d917fbbba78300a82a1ccb4cff/i-img900x1200-1751144021093084gmzb2990.jpg?pri=l&w=300&h=300&up=0&nf_src=sy&nf_path=images/auc/pc/top/image/1.0.3/na_170x170.png&nf_st=200",
      "target_m_price": "32,000円",
      "time_m": 240,
      "needs_photo_check": true,
      "is_white_sneaker": false,
      "needs_sole_warning": false,
      "keyword": "クリスチャンルブタン シューズ"
    },
    {
      "title": "GUCCI グッチ テニス シューズ 1977 ローカット スニーカー SIZE:6 靴 ∠UP4290",
      "url": "https://auctions.yahoo.co.jp/jp/auction/j1137963601",
      "price_formatted": "9,900円",
      "profit_formatted": "6,250円",
      "expected_profit": 6250,
      "stars": "★★★★★",
      "condition": "やや傷や汚れあり",
      "remaining_time": "36分51秒",
      "img_url": "https://auc-pctr.c.yimg.jp/i/auctions.c.yimg.jp/images.auctions.yahoo.co.jp/image/dr000/auc0505/users/e01ceaff985fa99865d2292fb5abff0f71b36f2a/i-img1200x897-1716717922exenty286299.jpg?pri=l&w=300&h=300&up=0&nf_src=sy&nf_path=images/auc/pc/top/image/1.0.3/na_170x170.png&nf_st=200",
      "target_m_price": "20,000円",
      "time_m": 36,
      "needs_photo_check": true,
      "is_white_sneaker": false,
      "needs_sole_warning": false,
      "keyword": "グッチ スニーカー シューズ"
    },
    {
      "title": "PRADA◆ローカットスニーカー/US8/BLK/2OG 064",
      "url": "https://auctions.yahoo.co.jp/jp/auction/l1208874019",
      "price_formatted": "17,160円",
      "profit_formatted": "6,190円",
      "expected_profit": 6190,
      "stars": "★★★★★",
      "condition": "やや傷や汚れあり",
      "remaining_time": "4時間",
      "img_url": "https://auc-pctr.c.yimg.jp/i/auctions.c.yimg.jp/images.auctions.yahoo.co.jp/image/dr000/auc0111/user/3641761cb5965ae1c25e46fef128dc48024c74d917fbbba78300a82a1ccb4cff/i-img900x1200-17638423432889k6pbvo57177.jpg?pri=l&w=300&h=300&up=0&nf_src=sy&nf_path=images/auc/pc/top/image/1.0.3/na_170x170.png&nf_st=200",
      "target_m_price": "28,000円",
      "time_m": 240,
      "needs_photo_check": true,
      "is_white_sneaker": false,
      "needs_sole_warning": false,
      "keyword": "プラダ スニーカー シューズ"
    },
    {
      "title": "LOEWE◆サンダル/36/ORN",
      "url": "https://auctions.yahoo.co.jp/jp/auction/s1157745525",
      "price_formatted": "17,160円",
      "profit_formatted": "6,190円",
      "expected_profit": 6190,
      "stars": "★★★★★",
      "condition": "やや傷や汚れあり",
      "remaining_time": "32分24秒",
      "img_url": "https://auc-pctr.c.yimg.jp/i/auctions.c.yimg.jp/images.auctions.yahoo.co.jp/image/dr000/auc0510/user/3641761cb5965ae1c25e46fef128dc48024c74d917fbbba78300a82a1ccb4cff/i-img900x1200-17294299762350sqo4oh290528.jpg?pri=l&w=300&h=300&up=0&nf_src=sy&nf_path=images/auc/pc/top/image/1.0.3/na_170x170.png&nf_st=200",
      "target_m_price": "28,000円",
      "time_m": 32,
      "needs_photo_check": true,
      "is_white_sneaker": false,
      "needs_sole_warning": false,
      "keyword": "ロエベ シューズ"
    },
    {
      "title": "[★] agnes b アニエスベー ストライプ がま口 ウォレット 口金 札入れ 長 財布 緑 ■■ レディース ○",
      "url": "https://auctions.yahoo.co.jp/jp/auction/d1224352699",
      "price_formatted": "1,536円",
      "profit_formatted": "6,144円",
      "expected_profit": 6144,
      "stars": "★★★★★",
      "condition": "未使用に近い / サイズ: 判定不要",
      "remaining_time": "22時間",
      "img_url": "https://auc-pctr.c.yimg.jp/i/auctions.c.yimg.jp/images.auctions.yahoo.co.jp/image/dr000/auc0203/user/8f5159001fa365b03e9cc956a53af0ea777394f3dc441ab5502c7ba0f973ee05/i-img756x1008-17745733129745imjqcj27.jpg?pri=l&w=300&h=300&up=0&nf_src=sy&nf_path=images/auc/pc/top/image/1.0.3/na_170x170.png&nf_st=200",
      "target_m_price": "9,500円",
      "time_m": 1320,
      "needs_photo_check": false,
      "is_white_sneaker": false,
      "needs_sole_warning": false,
      "keyword": "アニエスベー がま口"
    },
    {
      "title": "Dr.Martens(ドクターマーチン) 1461 MONO WHITE 3EYE BOOTS 3 ホール 中古 古着 1223",
      "url": "https://auctions.yahoo.co.jp/jp/auction/h1186212795",
      "price_formatted": "4,609円",
      "profit_formatted": "6,141円",
      "expected_profit": 6141,
      "stars": "★★★★★",
      "condition": "未使用に近い",
      "remaining_time": "2時間",
      "img_url": "https://auc-pctr.c.yimg.jp/i/auctions.c.yimg.jp/images.auctions.yahoo.co.jp/image/dr000/auc0105/user/02537f801bf6427ee25e01f2229c06376f5ae84f829d8e2dd64b405ad5a51969/i-img1200x1200-174814385175308xnnnr19293.jpg?pri=l&w=300&h=300&up=0&nf_src=sy&nf_path=images/auc/pc/top/image/1.0.3/na_170x170.png&nf_st=200",
      "target_m_price": "14,000円",
      "time_m": 120,
      "needs_photo_check": false,
      "is_white_sneaker": true,
      "needs_sole_warning": false,
      "keyword": "ドクターマーチン ブーツ 3ホール"
    },
    {
      "title": "P9455R49　▼CELINE セリーヌ▼　▼CELINE セリーヌ▼　TRIOMPHE トリオンフ ローレースアップ レザースニーカー ホワイト 38/24cm 白 黒",
      "url": "https://auctions.yahoo.co.jp/jp/auction/v1190225494",
      "price_formatted": "15,890円",
      "profit_formatted": "6,020円",
      "expected_profit": 6020,
      "stars": "★★★★★",
      "condition": "やや傷や汚れあり / サイズ: 24.0cm (L判OK)",
      "remaining_time": "53分24秒",
      "img_url": "https://auc-pctr.c.yimg.jp/i/auctions.c.yimg.jp/images.auctions.yahoo.co.jp/image/dr000/auc0106/user/135a3eb2e71b08eae8d8d189bad75942ffc0d51ca7cf0ba68b19a3e36f24edd7/i-img640x640-17508538743703fhn0gc13882.jpg?pri=l&w=300&h=300&up=0&nf_src=sy&nf_path=images/auc/pc/top/image/1.0.3/na_170x170.png&nf_st=200",
      "target_m_price": "26,400円",
      "time_m": 53,
      "needs_photo_check": true,
      "is_white_sneaker": true,
      "needs_sole_warning": false,
      "keyword": "セリーヌ シューズ"
    },
    {
      "title": "◇ adidas アディダス スニーカー サイズ23.0 レッド レディース E",
      "url": "https://auctions.yahoo.co.jp/jp/auction/u1209783113",
      "price_formatted": "468円",
      "profit_formatted": "5,782円",
      "expected_profit": 5782,
      "stars": "★★★★★",
      "condition": "未使用に近い",
      "remaining_time": "53秒",
      "img_url": "https://auc-pctr.c.yimg.jp/i/auctions.c.yimg.jp/images.auctions.yahoo.co.jp/image/dr000/auc0111/user/3eae7ab3e3789d02c229d8d277fb7babb824edbfa53bf14b591e86635b870530/i-img500x500-17644835569941ilhdaa93393.jpg?pri=l&w=300&h=300&up=0&nf_src=sy&nf_path=images/auc/pc/top/image/1.0.3/na_170x170.png&nf_st=200",
      "target_m_price": "9,000円",
      "time_m": 1,
      "needs_photo_check": false,
      "is_white_sneaker": false,
      "needs_sole_warning": false,
      "keyword": "アディダス スニーカー"
    },
    {
      "title": "GUCCI◆ローカットスニーカー/-/BLK/473974 35 04Z",
      "url": "https://auctions.yahoo.co.jp/jp/auction/p1214649430",
      "price_formatted": "10,560円",
      "profit_formatted": "5,590円",
      "expected_profit": 5590,
      "stars": "★★★★★",
      "condition": "やや傷や汚れあり",
      "remaining_time": "5時間",
      "img_url": "https://auc-pctr.c.yimg.jp/i/auctions.c.yimg.jp/images.auctions.yahoo.co.jp/image/dr000/auc0201/user/3641761cb5965ae1c25e46fef128dc48024c74d917fbbba78300a82a1ccb4cff/i-img900x1200-17674741420188smgch93609.jpg?pri=l&w=300&h=300&up=0&nf_src=sy&nf_path=images/auc/pc/top/image/1.0.3/na_170x170.png&nf_st=200",
      "target_m_price": "20,000円",
      "time_m": 300,
      "needs_photo_check": true,
      "is_white_sneaker": false,
      "needs_sole_warning": false,
      "keyword": "グッチ スニーカー シューズ"
    },
    {
      "title": "GUCCI◆スリッポン/ローカットスニーカー/-/NVY",
      "url": "https://auctions.yahoo.co.jp/jp/auction/f1225030250",
      "price_formatted": "10,560円",
      "profit_formatted": "5,590円",
      "expected_profit": 5590,
      "stars": "★★★★★",
      "condition": "やや傷や汚れあり",
      "remaining_time": "5時間",
      "img_url": "https://auc-pctr.c.yimg.jp/i/auctions.c.yimg.jp/images.auctions.yahoo.co.jp/image/dr000/auc0204/user/3641761cb5965ae1c25e46fef128dc48024c74d917fbbba78300a82a1ccb4cff/i-img900x1200-177506215713745ucpol36.jpg?pri=l&w=300&h=300&up=0&nf_src=sy&nf_path=images/auc/pc/top/image/1.0.3/na_170x170.png&nf_st=200",
      "target_m_price": "20,000円",
      "time_m": 300,
      "needs_photo_check": true,
      "is_white_sneaker": false,
      "needs_sole_warning": false,
      "keyword": "グッチ スニーカー シューズ"
    },
    {
      "title": "フルラ FURLA キーリング 付 コインケース パス ケース 黄色 イエロー レザー 小銭入れ カード入れ 名刺入れ ビジネス 小物【中古】sh1693",
      "url": "https://auctions.yahoo.co.jp/jp/auction/k1229421757",
      "price_formatted": "3,520円",
      "profit_formatted": "5,510円",
      "expected_profit": 5510,
      "stars": "★★★★★",
      "condition": "未使用に近い / サイズ: 判定不要",
      "remaining_time": "4時間",
      "img_url": "https://auc-pctr.c.yimg.jp/i/auctions.c.yimg.jp/images.auctions.yahoo.co.jp/image/dr000/auc0205/user/b54bd7f57d5c78d1c7fa96fad1b4bcb5aca05bbc64673bfd6150e10ec5d577bd/i-img640x480-17783949017358suhmut35.jpg?pri=l&w=300&h=300&up=0&nf_src=sy&nf_path=images/auc/pc/top/image/1.0.3/na_170x170.png&nf_st=200",
      "target_m_price": "11,000円",
      "time_m": 240,
      "needs_photo_check": false,
      "is_white_sneaker": false,
      "needs_sole_warning": false,
      "keyword": "フルラ 財布"
    },
    {
      "title": "PELLICO / ペリーコ パテントレザー メタリック ポインテッドトゥ ヒール パンプス",
      "url": "https://auctions.yahoo.co.jp/jp/auction/k1203402981",
      "price_formatted": "3,465円",
      "profit_formatted": "5,485円",
      "expected_profit": 5485,
      "stars": "★★★★★",
      "condition": "未使用に近い",
      "remaining_time": "23分2秒",
      "img_url": "https://auc-pctr.c.yimg.jp/i/auctions.c.yimg.jp/images.auctions.yahoo.co.jp/image/dr000/auc0110/user/3e28230cf31c7dcb42f5a34eb3441bad1f1270e37038cef0bee276e6a8027723/i-img1200x1200-17600627836538bgbehd4853.jpg?pri=l&w=300&h=300&up=0&nf_src=sy&nf_path=images/auc/pc/top/image/1.0.3/na_170x170.png&nf_st=200",
      "target_m_price": "12,000円",
      "time_m": 23,
      "needs_photo_check": false,
      "is_white_sneaker": false,
      "needs_sole_warning": false,
      "keyword": "ペリーコ シューズ"
    },
    {
      "title": "PELLICO / ペリーコ | パテントレザー ストラップ ヒール パンプス サンダル | 35 | オレンジ | レディース",
      "url": "https://auctions.yahoo.co.jp/jp/auction/m1186682346",
      "price_formatted": "3,465円",
      "profit_formatted": "5,485円",
      "expected_profit": 5485,
      "stars": "★★★★★",
      "condition": "未使用に近い",
      "remaining_time": "4時間",
      "img_url": "https://auc-pctr.c.yimg.jp/i/auctions.c.yimg.jp/images.auctions.yahoo.co.jp/image/dr000/auc0105/user/3e28230cf31c7dcb42f5a34eb3441bad1f1270e37038cef0bee276e6a8027723/i-img1200x1200-17484828773563u1tzu810270.jpg?pri=l&w=300&h=300&up=0&nf_src=sy&nf_path=images/auc/pc/top/image/1.0.3/na_170x170.png&nf_st=200",
      "target_m_price": "12,000円",
      "time_m": 240,
      "needs_photo_check": false,
      "is_white_sneaker": false,
      "needs_sole_warning": false,
      "keyword": "ペリーコ シューズ"
    },
    {
      "title": "PELLICO / ペリーコ パテントレザー メタリック ポインテッドトゥ ヒール パンプス",
      "url": "https://auctions.yahoo.co.jp/jp/auction/k1203402981",
      "price_formatted": "3,465円",
      "profit_formatted": "5,485円",
      "expected_profit": 5485,
      "stars": "★★★★★",
      "condition": "未使用に近い",
      "remaining_time": "19分38秒",
      "img_url": "https://auc-pctr.c.yimg.jp/i/auctions.c.yimg.jp/images.auctions.yahoo.co.jp/image/dr000/auc0110/user/3e28230cf31c7dcb42f5a34eb3441bad1f1270e37038cef0bee276e6a8027723/i-img1200x1200-17600627836538bgbehd4853.jpg?pri=l&w=300&h=300&up=0&nf_src=sy&nf_path=images/auc/pc/top/image/1.0.3/na_170x170.png&nf_st=200",
      "target_m_price": "12,000円",
      "time_m": 19,
      "needs_photo_check": false,
      "is_white_sneaker": false,
      "needs_sole_warning": false,
      "keyword": "ペリーコ シューズ パンプス"
    },
    {
      "title": "PELLICO / ペリーコ | パテントレザー ストラップ ヒール パンプス サンダル | 35 | オレンジ | レディース",
      "url": "https://auctions.yahoo.co.jp/jp/auction/m1186682346",
      "price_formatted": "3,465円",
      "profit_formatted": "5,485円",
      "expected_profit": 5485,
      "stars": "★★★★★",
      "condition": "未使用に近い",
      "remaining_time": "4時間",
      "img_url": "https://auc-pctr.c.yimg.jp/i/auctions.c.yimg.jp/images.auctions.yahoo.co.jp/image/dr000/auc0105/user/3e28230cf31c7dcb42f5a34eb3441bad1f1270e37038cef0bee276e6a8027723/i-img1200x1200-17484828773563u1tzu810270.jpg?pri=l&w=300&h=300&up=0&nf_src=sy&nf_path=images/auc/pc/top/image/1.0.3/na_170x170.png&nf_st=200",
      "target_m_price": "12,000円",
      "time_m": 240,
      "needs_photo_check": false,
      "is_white_sneaker": false,
      "needs_sole_warning": false,
      "keyword": "ペリーコ シューズ パンプス"
    },
    {
      "title": "PELLICO / ペリーコ レザー ヒール ブーティ",
      "url": "https://auctions.yahoo.co.jp/jp/auction/1213560030",
      "price_formatted": "3,465円",
      "profit_formatted": "5,485円",
      "expected_profit": 5485,
      "stars": "★★★★★",
      "condition": "未使用に近い",
      "remaining_time": "5時間",
      "img_url": "https://auc-pctr.c.yimg.jp/i/auctions.c.yimg.jp/images.auctions.yahoo.co.jp/image/dr000/auc0112/user/3e28230cf31c7dcb42f5a34eb3441bad1f1270e37038cef0bee276e6a8027723/i-img1200x1200-17665513129754sjvssr35108.jpg?pri=l&w=300&h=300&up=0&nf_src=sy&nf_path=images/auc/pc/top/image/1.0.3/na_170x170.png&nf_st=200",
      "target_m_price": "12,000円",
      "time_m": 300,
      "needs_photo_check": false,
      "is_white_sneaker": false,
      "needs_sole_warning": false,
      "keyword": "ペリーコ シューズ パンプス"
    },
    {
      "title": "未開封品 エイコー 維新の奇跡 坂本龍馬 ストライクこれくしょんVol.1 モンスターストライク",
      "url": "https://auctions.yahoo.co.jp/jp/auction/r1211771074",
      "price_formatted": "990円",
      "profit_formatted": "5,260円",
      "expected_profit": 5260,
      "stars": "★★★★★",
      "condition": "やや傷や汚れあり / サイズ: 判定不要",
      "remaining_time": "22時間",
      "img_url": "https://auc-pctr.c.yimg.jp/i/auctions.c.yimg.jp/images.auctions.yahoo.co.jp/image/dr000/auc0112/user/4de85e37f2cc010ee64b5d765ea5758a79581da8e31f1e79dbb068181bd11d56/i-img1200x900-1765268667560670xl2817261.jpg?pri=l&w=300&h=300&up=0&nf_src=sy&nf_path=images/auc/pc/top/image/1.0.3/na_170x170.png&nf_st=200",
      "target_m_price": "9,000円",
      "time_m": 1320,
      "needs_photo_check": true,
      "is_white_sneaker": false,
      "needs_sole_warning": false,
      "keyword": "坂本これくしょん"
    },
    {
      "title": "MIU MIU◆ローカットスニーカー/35.5/BLK",
      "url": "https://auctions.yahoo.co.jp/jp/auction/d1227774441",
      "price_formatted": "12,760円",
      "profit_formatted": "5,190円",
      "expected_profit": 5190,
      "stars": "★★★★★",
      "condition": "やや傷や汚れあり",
      "remaining_time": "2時間",
      "img_url": "https://auc-pctr.c.yimg.jp/i/auctions.c.yimg.jp/images.auctions.yahoo.co.jp/image/dr000/auc0204/user/3641761cb5965ae1c25e46fef128dc48024c74d917fbbba78300a82a1ccb4cff/i-img900x1200-17770719535475zyakxe422206.jpg?pri=l&w=300&h=300&up=0&nf_src=sy&nf_path=images/auc/pc/top/image/1.0.3/na_170x170.png&nf_st=200",
      "target_m_price": "22,000円",
      "time_m": 120,
      "needs_photo_check": true,
      "is_white_sneaker": false,
      "needs_sole_warning": false,
      "keyword": "ミュウミュウ シューズ"
    },
    {
      "title": "LOEWE◆シューズ/40/ORN",
      "url": "https://auctions.yahoo.co.jp/jp/auction/f1221319280",
      "price_formatted": "18,260円",
      "profit_formatted": "5,090円",
      "expected_profit": 5090,
      "stars": "★★★★★",
      "condition": "やや傷や汚れあり",
      "remaining_time": "19時間",
      "img_url": "https://auc-pctr.c.yimg.jp/i/auctions.c.yimg.jp/images.auctions.yahoo.co.jp/image/dr000/auc0203/user/3641761cb5965ae1c25e46fef128dc48024c74d917fbbba78300a82a1ccb4cff/i-img900x1200-17723220810598rldrq335.jpg?pri=l&w=300&h=300&up=0&nf_src=sy&nf_path=images/auc/pc/top/image/1.0.3/na_170x170.png&nf_st=200",
      "target_m_price": "28,000円",
      "time_m": 1140,
      "needs_photo_check": true,
      "is_white_sneaker": false,
      "needs_sole_warning": false,
      "keyword": "ロエベ シューズ"
    },
    {
      "title": "FURLA◆2つ折り財布/レザー/BEG/レディース",
      "url": "https://auctions.yahoo.co.jp/jp/auction/u1190526565",
      "price_formatted": "3,960円",
      "profit_formatted": "5,070円",
      "expected_profit": 5070,
      "stars": "★★★★★",
      "condition": "未使用に近い / サイズ: 判定不要",
      "remaining_time": "4時間",
      "img_url": "https://auc-pctr.c.yimg.jp/i/auctions.c.yimg.jp/images.auctions.yahoo.co.jp/image/dr000/auc0106/user/3641761cb5965ae1c25e46fef128dc48024c74d917fbbba78300a82a1ccb4cff/i-img900x1200-17510567837285ys5auz8804.jpg?pri=l&w=300&h=300&up=0&nf_src=sy&nf_path=images/auc/pc/top/image/1.0.3/na_170x170.png&nf_st=200",
      "target_m_price": "11,000円",
      "time_m": 240,
      "needs_photo_check": false,
      "is_white_sneaker": false,
      "needs_sole_warning": false,
      "keyword": "フルラ 財布"
    },
    {
      "title": "◇ converse コンバース ローカット レースアップ スニーカー シューズ サイズ6 1/2 ブラック レディース P",
      "url": "https://auctions.yahoo.co.jp/jp/auction/g1209827971",
      "price_formatted": "468円",
      "profit_formatted": "4,882円",
      "expected_profit": 4882,
      "stars": "★★★★☆",
      "condition": "未使用に近い",
      "remaining_time": "16分50秒",
      "img_url": "https://auc-pctr.c.yimg.jp/i/auctions.c.yimg.jp/images.auctions.yahoo.co.jp/image/dr000/auc0112/user/3eae7ab3e3789d02c229d8d277fb7babb824edbfa53bf14b591e86635b870530/i-img500x666-176453596976826imtuy19972.jpg?pri=l&w=300&h=300&up=0&nf_src=sy&nf_path=images/auc/pc/top/image/1.0.3/na_170x170.png&nf_st=200",
      "target_m_price": "8,000円",
      "time_m": 16,
      "needs_photo_check": false,
      "is_white_sneaker": false,
      "needs_sole_warning": false,
      "keyword": "コンバース スニーカー"
    },
    {
      "title": "◇ CONVERSE カジュアル レースアップ ハイカット ロゴ スニーカー サイズ23.5 ブラック レディース E",
      "url": "https://auctions.yahoo.co.jp/jp/auction/f1209737893",
      "price_formatted": "468円",
      "profit_formatted": "4,882円",
      "expected_profit": 4882,
      "stars": "★★★★☆",
      "condition": "未使用に近い",
      "remaining_time": "17分5秒",
      "img_url": "https://auc-pctr.c.yimg.jp/i/auctions.c.yimg.jp/images.auctions.yahoo.co.jp/image/dr000/auc0111/user/3eae7ab3e3789d02c229d8d277fb7babb824edbfa53bf14b591e86635b870530/i-img500x500-176446656243339tnohs2097.jpg?pri=l&w=300&h=300&up=0&nf_src=sy&nf_path=images/auc/pc/top/image/1.0.3/na_170x170.png&nf_st=200",
      "target_m_price": "8,000円",
      "time_m": 17,
      "needs_photo_check": false,
      "is_white_sneaker": false,
      "needs_sole_warning": false,
      "keyword": "コンバース スニーカー"
    },
    {
      "title": "◇ FILA フィラ シンプル カジュアル 厚底 きれいめ アウトドア アクティブ スニーカー サイズ25 グレー レディース E",
      "url": "https://auctions.yahoo.co.jp/jp/auction/g1209777707",
      "price_formatted": "468円",
      "profit_formatted": "4,882円",
      "expected_profit": 4882,
      "stars": "★★★★☆",
      "condition": "未使用に近い",
      "remaining_time": "18分10秒",
      "img_url": "https://auc-pctr.c.yimg.jp/i/auctions.c.yimg.jp/images.auctions.yahoo.co.jp/image/dr000/auc0111/user/3eae7ab3e3789d02c229d8d277fb7babb824edbfa53bf14b591e86635b870530/i-img500x500-17644898263421lcsrjd52149.jpg?pri=l&w=300&h=300&up=0&nf_src=sy&nf_path=images/auc/pc/top/image/1.0.3/na_170x170.png&nf_st=200",
      "target_m_price": "8,000円",
      "time_m": 18,
      "needs_photo_check": false,
      "is_white_sneaker": false,
      "needs_sole_warning": false,
      "keyword": "コンバース スニーカー"
    },
    {
      "title": "◇ VANS ヴァンズ スニーカー サイズ24.0 ブラック メンズ E",
      "url": "https://auctions.yahoo.co.jp/jp/auction/b1209674879",
      "price_formatted": "495円",
      "profit_formatted": "4,855円",
      "expected_profit": 4855,
      "stars": "★★★★☆",
      "condition": "未使用に近い",
      "remaining_time": "15分10秒",
      "img_url": "https://auc-pctr.c.yimg.jp/i/auctions.c.yimg.jp/images.auctions.yahoo.co.jp/image/dr000/auc0111/user/3eae7ab3e3789d02c229d8d277fb7babb824edbfa53bf14b591e86635b870530/i-img500x500-17643940092900gvnrff34.jpg?pri=l&w=300&h=300&up=0&nf_src=sy&nf_path=images/auc/pc/top/image/1.0.3/na_170x170.png&nf_st=200",
      "target_m_price": "8,000円",
      "time_m": 15,
      "needs_photo_check": false,
      "is_white_sneaker": false,
      "needs_sole_warning": false,
      "keyword": "コンバース スニーカー"
    },
    {
      "title": "◇ CONVERSE コンバース M5039 スニーカー サイズ26.5 ブラック メンズ E",
      "url": "https://auctions.yahoo.co.jp/jp/auction/j1208022444",
      "price_formatted": "495円",
      "profit_formatted": "4,855円",
      "expected_profit": 4855,
      "stars": "★★★★☆",
      "condition": "未使用に近い",
      "remaining_time": "19分30秒",
      "img_url": "https://auc-pctr.c.yimg.jp/i/auctions.c.yimg.jp/images.auctions.yahoo.co.jp/image/dr000/auc0111/user/3eae7ab3e3789d02c229d8d277fb7babb824edbfa53bf14b591e86635b870530/i-img500x500-17632481824304x8nolz81794.jpg?pri=l&w=300&h=300&up=0&nf_src=sy&nf_path=images/auc/pc/top/image/1.0.3/na_170x170.png&nf_st=200",
      "target_m_price": "8,000円",
      "time_m": 19,
      "needs_photo_check": false,
      "is_white_sneaker": false,
      "needs_sole_warning": false,
      "keyword": "コンバース スニーカー"
    },
    {
      "title": "DIANA/ダイアナ ベルトデザインミドルヒールスエードロングブーツ ブラウン23 am111",
      "url": "https://auctions.yahoo.co.jp/jp/auction/k1170741173",
      "price_formatted": "550円",
      "profit_formatted": "4,800円",
      "expected_profit": 4800,
      "stars": "★★★★☆",
      "condition": "未使用に近い",
      "remaining_time": "21時間",
      "img_url": "https://auc-pctr.c.yimg.jp/i/auctions.c.yimg.jp/images.auctions.yahoo.co.jp/image/dr000/auc0101/user/234195a13e9a09454b4142df763ffbbaee1f14c5954e5af35ec3a861f9ff0493/i-img937x1200-17377669448400tuhzt0175254.jpg?pri=l&w=300&h=300&up=0&nf_src=sy&nf_path=images/auc/pc/top/image/1.0.3/na_170x170.png&nf_st=200",
      "target_m_price": "8,000円",
      "time_m": 1260,
      "needs_photo_check": false,
      "is_white_sneaker": false,
      "needs_sole_warning": false,
      "keyword": "ダイアナ パンプス ブーツ"
    },
    {
      "title": "CELINE◆サイドゴアブーツ/35/BLK/レザー",
      "url": "https://auctions.yahoo.co.jp/jp/auction/k1223757328",
      "price_formatted": "14,960円",
      "profit_formatted": "4,790円",
      "expected_profit": 4790,
      "stars": "★★★★☆",
      "condition": "やや傷や汚れあり",
      "remaining_time": "3時間",
      "img_url": "https://auc-pctr.c.yimg.jp/i/auctions.c.yimg.jp/images.auctions.yahoo.co.jp/image/dr000/auc0203/user/3641761cb5965ae1c25e46fef128dc48024c74d917fbbba78300a82a1ccb4cff/i-img900x1200-17741289419783b5shww168650.jpg?pri=l&w=300&h=300&up=0&nf_src=sy&nf_path=images/auc/pc/top/image/1.0.3/na_170x170.png&nf_st=200",
      "target_m_price": "24,000円",
      "time_m": 180,
      "needs_photo_check": true,
      "is_white_sneaker": false,
      "needs_sole_warning": false,
      "keyword": "セリーヌ シューズ"
    },
    {
      "title": "genten ゲンテン　カットワーク／White 長財布",
      "url": "https://auctions.yahoo.co.jp/jp/auction/q1198129569",
      "price_formatted": "4,224円",
      "profit_formatted": "4,726円",
      "expected_profit": 4726,
      "stars": "★★★★☆",
      "condition": "やや傷や汚れあり / サイズ: 判定不要",
      "remaining_time": "1日",
      "img_url": "https://auc-pctr.c.yimg.jp/i/auctions.c.yimg.jp/images.auctions.yahoo.co.jp/image/dr000/auc0108/user/4de85e37f2cc010ee64b5d765ea5758a79581da8e31f1e79dbb068181bd11d56/i-img1200x900-17564344048773lnn05r36.jpg?pri=l&w=300&h=300&up=0&nf_src=sy&nf_path=images/auc/pc/top/image/1.0.3/na_170x170.png&nf_st=200",
      "target_m_price": "12,000円",
      "time_m": 1440,
      "needs_photo_check": true,
      "is_white_sneaker": false,
      "needs_sole_warning": false,
      "keyword": "ゲンテン カットワーク"
    },
    {
      "title": "genten ゲンテン　カットワーク／がま口 長財布",
      "url": "https://auctions.yahoo.co.jp/jp/auction/j1198124545",
      "price_formatted": "4,224円",
      "profit_formatted": "4,726円",
      "expected_profit": 4726,
      "stars": "★★★★☆",
      "condition": "やや傷や汚れあり / サイズ: 判定不要",
      "remaining_time": "1日",
      "img_url": "https://auc-pctr.c.yimg.jp/i/auctions.c.yimg.jp/images.auctions.yahoo.co.jp/image/dr000/auc0108/user/4de85e37f2cc010ee64b5d765ea5758a79581da8e31f1e79dbb068181bd11d56/i-img1200x900-17564353475311hsslev13891.jpg?pri=l&w=300&h=300&up=0&nf_src=sy&nf_path=images/auc/pc/top/image/1.0.3/na_170x170.png&nf_st=200",
      "target_m_price": "12,000円",
      "time_m": 1440,
      "needs_photo_check": true,
      "is_white_sneaker": false,
      "needs_sole_warning": false,
      "keyword": "ゲンテン カットワーク"
    },
    {
      "title": "BOTTEGA VENETA◆ピロー/PILLOW/ローカットスニーカー/-/WHT",
      "url": "https://auctions.yahoo.co.jp/jp/auction/q1196385369",
      "price_formatted": "20,460円",
      "profit_formatted": "4,690円",
      "expected_profit": 4690,
      "stars": "★★★★☆",
      "condition": "やや傷や汚れあり",
      "remaining_time": "4時間",
      "img_url": "https://auc-pctr.c.yimg.jp/i/auctions.c.yimg.jp/images.auctions.yahoo.co.jp/image/dr000/auc0108/user/3641761cb5965ae1c25e46fef128dc48024c74d917fbbba78300a82a1ccb4cff/i-img900x1200-17552063394689wpozqu33.jpg?pri=l&w=300&h=300&up=0&nf_src=sy&nf_path=images/auc/pc/top/image/1.0.3/na_170x170.png&nf_st=200",
      "target_m_price": "30,000円",
      "time_m": 240,
      "needs_photo_check": true,
      "is_white_sneaker": false,
      "needs_sole_warning": false,
      "keyword": "ボッテガヴェネタ シューズ"
    },
    {
      "title": "Christian Louboutin◆パンプス/36.5/BLK",
      "url": "https://auctions.yahoo.co.jp/jp/auction/q1214647893",
      "price_formatted": "22,660円",
      "profit_formatted": "4,290円",
      "expected_profit": 4290,
      "stars": "★★★★☆",
      "condition": "やや傷や汚れあり",
      "remaining_time": "22分51秒",
      "img_url": "https://auc-pctr.c.yimg.jp/i/auctions.c.yimg.jp/images.auctions.yahoo.co.jp/image/dr000/auc0201/user/3641761cb5965ae1c25e46fef128dc48024c74d917fbbba78300a82a1ccb4cff/i-img900x1200-176747851814033sswld11945.jpg?pri=l&w=300&h=300&up=0&nf_src=sy&nf_path=images/auc/pc/top/image/1.0.3/na_170x170.png&nf_st=200",
      "target_m_price": "32,000円",
      "time_m": 22,
      "needs_photo_check": true,
      "is_white_sneaker": false,
      "needs_sole_warning": false,
      "keyword": "クリスチャンルブタン シューズ"
    },
    {
      "title": "美品 シャネル 90年代 ヴィンテージ アーカイブ マトラッセ レザー ポンテッドトゥ パンプス ヒール サンダル 黒 36 23cm レディース",
      "url": "https://auctions.yahoo.co.jp/jp/auction/l1225248302",
      "price_formatted": "16,600円",
      "profit_formatted": "4,050円",
      "expected_profit": 4050,
      "stars": "★★★★☆",
      "condition": "やや傷や汚れあり / サイズ: 23.0cm (L判OK)",
      "remaining_time": "1日",
      "img_url": "https://auc-pctr.c.yimg.jp/i/auctions.c.yimg.jp/images.auctions.yahoo.co.jp/image/dr000/auc0204/user/0ff4ba0ada4039f8f03a8db98bf81add4c4b05538aaf38c47365d895f73cc3f5/i-img1000x1000-17752046249263kj8lll36.jpg?pri=l&w=300&h=300&up=0&nf_src=sy&nf_path=images/auc/pc/top/image/1.0.3/na_170x170.png&nf_st=200",
      "target_m_price": "25,000円",
      "time_m": 1440,
      "needs_photo_check": true,
      "is_white_sneaker": false,
      "needs_sole_warning": false,
      "keyword": "シャネル サンダル パンプス"
    },
    {
      "title": "FURLA◆BABYLON/ラウンドファスナー長財布/レザー/BLU/無地/レディース//",
      "url": "https://auctions.yahoo.co.jp/jp/auction/x1230985080",
      "price_formatted": "5,060円",
      "profit_formatted": "3,970円",
      "expected_profit": 3970,
      "stars": "★★★★☆",
      "condition": "未使用に近い / サイズ: 判定不要",
      "remaining_time": "46分24秒",
      "img_url": "https://auc-pctr.c.yimg.jp/i/auctions.c.yimg.jp/images.auctions.yahoo.co.jp/image/dr000/auc0205/user/3641761cb5965ae1c25e46fef128dc48024c74d917fbbba78300a82a1ccb4cff/i-img900x1200-17795752562455h9ryc733.jpg?pri=l&w=300&h=300&up=0&nf_src=sy&nf_path=images/auc/pc/top/image/1.0.3/na_170x170.png&nf_st=200",
      "target_m_price": "11,000円",
      "time_m": 46,
      "needs_photo_check": false,
      "is_white_sneaker": false,
      "needs_sole_warning": false,
      "keyword": "フルラ 財布"
    },
    {
      "title": "HERMES エルメス ジミー スウェード ムートン ハイカット スニーカー シューズ レディース ベージュ36",
      "url": "https://auctions.yahoo.co.jp/jp/auction/h1222406032",
      "price_formatted": "43,890円",
      "profit_formatted": "3,760円",
      "expected_profit": 3760,
      "stars": "★★★★☆",
      "condition": "未使用に近い",
      "remaining_time": "3時間",
      "img_url": "https://auc-pctr.c.yimg.jp/i/auctions.c.yimg.jp/images.auctions.yahoo.co.jp/image/dr000/auc0203/user/a17dd56b8ac5b12557f8bfbffe94125fe72b9c80c20dc5a437911e1a37442081/i-img1000x1000-17731141596367si89lh83497.jpg?pri=l&w=300&h=300&up=0&nf_src=sy&nf_path=images/auc/pc/top/image/1.0.3/na_170x170.png&nf_st=200",
      "target_m_price": "55,000円",
      "time_m": 180,
      "needs_photo_check": false,
      "is_white_sneaker": false,
      "needs_sole_warning": false,
      "keyword": "エルメス シューズ サンダル"
    },
    {
      "title": "■【YS-1】 アニエスベー agnes b. 2つ折り 財布 ■ 赤系 がま口 小銭入れ有り 横12,5cm×縦10,5cm 【同梱可能商品】K■",
      "url": "https://auctions.yahoo.co.jp/jp/auction/t1074912945",
      "price_formatted": "468円",
      "profit_formatted": "3,162円",
      "expected_profit": 3162,
      "stars": "★★★★☆",
      "condition": "やや傷や汚れあり / サイズ: 判定不要",
      "remaining_time": "21時間",
      "img_url": "https://auc-pctr.c.yimg.jp/i/auctions.c.yimg.jp/images.auctions.yahoo.co.jp/image/dr000/auc0312/users/6bf6fab1414da1e70cec02922fe59e9fe2dc6670/i-img1200x900-1670552843otcc3c136852.jpg?pri=l&w=300&h=300&up=0&nf_src=sy&nf_path=images/auc/pc/top/image/1.0.3/na_170x170.png&nf_st=200",
      "target_m_price": "5,000円",
      "time_m": 1260,
      "needs_photo_check": true,
      "is_white_sneaker": false,
      "needs_sole_warning": false,
      "keyword": "アニエスベー がま口"
    },
    {
      "title": "PRADA◆ローカットスニーカー/UK7.5/KHK/スウェード/3476",
      "url": "https://auctions.yahoo.co.jp/jp/auction/s1204501377",
      "price_formatted": "20,460円",
      "profit_formatted": "2,890円",
      "expected_profit": 2890,
      "stars": "★★★☆☆",
      "condition": "やや傷や汚れあり",
      "remaining_time": "9時間",
      "img_url": "https://auc-pctr.c.yimg.jp/i/auctions.c.yimg.jp/images.auctions.yahoo.co.jp/image/dr000/auc0110/user/3641761cb5965ae1c25e46fef128dc48024c74d917fbbba78300a82a1ccb4cff/i-img900x1200-176083219343372hbb6y2093.jpg?pri=l&w=300&h=300&up=0&nf_src=sy&nf_path=images/auc/pc/top/image/1.0.3/na_170x170.png&nf_st=200",
      "target_m_price": "28,000円",
      "time_m": 540,
      "needs_photo_check": true,
      "is_white_sneaker": false,
      "needs_sole_warning": false,
      "keyword": "プラダ スニーカー シューズ"
    },
    {
      "title": "FURLA◆2つ折り財布/レザー/BLK/レディース//",
      "url": "https://auctions.yahoo.co.jp/jp/auction/e1204451623",
      "price_formatted": "6,160円",
      "profit_formatted": "2,870円",
      "expected_profit": 2870,
      "stars": "★★★☆☆",
      "condition": "未使用に近い / サイズ: 判定不要",
      "remaining_time": "6時間",
      "img_url": "https://auc-pctr.c.yimg.jp/i/auctions.c.yimg.jp/images.auctions.yahoo.co.jp/image/dr000/auc0110/user/3641761cb5965ae1c25e46fef128dc48024c74d917fbbba78300a82a1ccb4cff/i-img900x1200-176077818448751epdco8093.jpg?pri=l&w=300&h=300&up=0&nf_src=sy&nf_path=images/auc/pc/top/image/1.0.3/na_170x170.png&nf_st=200",
      "target_m_price": "11,000円",
      "time_m": 360,
      "needs_photo_check": false,
      "is_white_sneaker": false,
      "needs_sole_warning": false,
      "keyword": "フルラ 財布"
    },
    {
      "title": "【美品】 PELLICO / ペリーコ | チェック ヒールパンプス | 37 | ネイビー系 | レディース",
      "url": "https://auctions.yahoo.co.jp/jp/auction/f1174049261",
      "price_formatted": "6,237円",
      "profit_formatted": "2,713円",
      "expected_profit": 2713,
      "stars": "★★★☆☆",
      "condition": "未使用に近い",
      "remaining_time": "9分18秒",
      "img_url": "https://auc-pctr.c.yimg.jp/i/auctions.c.yimg.jp/images.auctions.yahoo.co.jp/image/dr000/auc0102/user/3e28230cf31c7dcb42f5a34eb3441bad1f1270e37038cef0bee276e6a8027723/i-img800x800-17399391510814v7s1nd165070.jpg?pri=l&w=300&h=300&up=0&nf_src=sy&nf_path=images/auc/pc/top/image/1.0.3/na_170x170.png&nf_st=200",
      "target_m_price": "12,000円",
      "time_m": 9,
      "needs_photo_check": false,
      "is_white_sneaker": false,
      "needs_sole_warning": false,
      "keyword": "ペリーコ シューズ"
    },
    {
      "title": "【美品】 PELLICO / ペリーコ | チェック ヒールパンプス | 37 | ネイビー系 | レディース",
      "url": "https://auctions.yahoo.co.jp/jp/auction/f1174049261",
      "price_formatted": "6,237円",
      "profit_formatted": "2,713円",
      "expected_profit": 2713,
      "stars": "★★★☆☆",
      "condition": "未使用に近い",
      "remaining_time": "5分54秒",
      "img_url": "https://auc-pctr.c.yimg.jp/i/auctions.c.yimg.jp/images.auctions.yahoo.co.jp/image/dr000/auc0102/user/3e28230cf31c7dcb42f5a34eb3441bad1f1270e37038cef0bee276e6a8027723/i-img800x800-17399391510814v7s1nd165070.jpg?pri=l&w=300&h=300&up=0&nf_src=sy&nf_path=images/auc/pc/top/image/1.0.3/na_170x170.png&nf_st=200",
      "target_m_price": "12,000円",
      "time_m": 5,
      "needs_photo_check": false,
      "is_white_sneaker": false,
      "needs_sole_warning": false,
      "keyword": "ペリーコ シューズ パンプス"
    },
    {
      "title": "CELINE◆ブーツ/36/BLK",
      "url": "https://auctions.yahoo.co.jp/jp/auction/r1226242706",
      "price_formatted": "17,160円",
      "profit_formatted": "2,590円",
      "expected_profit": 2590,
      "stars": "★★★☆☆",
      "condition": "やや傷や汚れあり",
      "remaining_time": "7時間",
      "img_url": "https://auc-pctr.c.yimg.jp/i/auctions.c.yimg.jp/images.auctions.yahoo.co.jp/image/dr000/auc0204/user/3641761cb5965ae1c25e46fef128dc48024c74d917fbbba78300a82a1ccb4cff/i-img900x1200-17759536985508tvnhjd16890.jpg?pri=l&w=300&h=300&up=0&nf_src=sy&nf_path=images/auc/pc/top/image/1.0.3/na_170x170.png&nf_st=200",
      "target_m_price": "24,000円",
      "time_m": 420,
      "needs_photo_check": true,
      "is_white_sneaker": false,
      "needs_sole_warning": false,
      "keyword": "セリーヌ シューズ"
    },
    {
      "title": "トリーバーチ トートバッグ 40913 ブラウン レザー 中古 チェーンショルダー 肩掛け ロゴ レディース TORY",
      "url": "https://auctions.yahoo.co.jp/jp/auction/g1229335413",
      "price_formatted": "11,800円",
      "profit_formatted": "2,550円",
      "expected_profit": 2550,
      "stars": "★★★☆☆",
      "condition": "未使用に近い / サイズ: 判定不要",
      "remaining_time": "2時間",
      "img_url": "https://auc-pctr.c.yimg.jp/i/auctions.c.yimg.jp/images.auctions.yahoo.co.jp/image/dr000/auc0205/user/e6589c0484641d08fb87fa70ca2ffa9ed5938f6371c52b5c4b67d75b28428b18/i-img1000x1000-177833682574486l6hrd1580.jpg?pri=l&w=300&h=300&up=0&nf_src=sy&nf_path=images/auc/pc/top/image/1.0.3/na_170x170.png&nf_st=200",
      "target_m_price": "18,000円",
      "time_m": 120,
      "needs_photo_check": false,
      "is_white_sneaker": false,
      "needs_sole_warning": false,
      "keyword": "トリーバーチ バッグ"
    },
    {
      "title": "Salvatore Ferragamo◆パンプス/-",
      "url": "https://auctions.yahoo.co.jp/jp/auction/s1193066819",
      "price_formatted": "2,860円",
      "profit_formatted": "2,490円",
      "expected_profit": 2490,
      "stars": "★★★☆☆",
      "condition": "やや傷や汚れあり",
      "remaining_time": "6分36秒",
      "img_url": "https://auc-pctr.c.yimg.jp/i/auctions.c.yimg.jp/images.auctions.yahoo.co.jp/image/dr000/auc0107/user/3641761cb5965ae1c25e46fef128dc48024c74d917fbbba78300a82a1ccb4cff/i-img900x1200-17527906192264ncskbd17172.jpg?pri=l&w=300&h=300&up=0&nf_src=sy&nf_path=images/auc/pc/top/image/1.0.3/na_170x170.png&nf_st=200",
      "target_m_price": "8,000円",
      "time_m": 6,
      "needs_photo_check": true,
      "is_white_sneaker": false,
      "needs_sole_warning": false,
      "keyword": "フェラガモ パンプス シューズ"
    },
    {
      "title": "BOTTEGA VENETA◆サンダル/-/ブラウン/スウェード",
      "url": "https://auctions.yahoo.co.jp/jp/auction/j1221324033",
      "price_formatted": "22,660円",
      "profit_formatted": "2,490円",
      "expected_profit": 2490,
      "stars": "★★★☆☆",
      "condition": "やや傷や汚れあり",
      "remaining_time": "7時間",
      "img_url": "https://auc-pctr.c.yimg.jp/i/auctions.c.yimg.jp/images.auctions.yahoo.co.jp/image/dr000/auc0203/user/3641761cb5965ae1c25e46fef128dc48024c74d917fbbba78300a82a1ccb4cff/i-img900x1200-17723272748481ilt2vy1574.jpg?pri=l&w=300&h=300&up=0&nf_src=sy&nf_path=images/auc/pc/top/image/1.0.3/na_170x170.png&nf_st=200",
      "target_m_price": "30,000円",
      "time_m": 420,
      "needs_photo_check": true,
      "is_white_sneaker": false,
      "needs_sole_warning": false,
      "keyword": "ボッテガヴェネタ シューズ"
    },
    {
      "title": "COLE HAAN◆ブーツ/-/BEG",
      "url": "https://auctions.yahoo.co.jp/jp/auction/p1153547373",
      "price_formatted": "2,860円",
      "profit_formatted": "2,490円",
      "expected_profit": 2490,
      "stars": "★★★☆☆",
      "condition": "やや傷や汚れあり",
      "remaining_time": "2時間",
      "img_url": "https://auc-pctr.c.yimg.jp/i/auctions.c.yimg.jp/images.auctions.yahoo.co.jp/image/dr000/auc0509/user/3641761cb5965ae1c25e46fef128dc48024c74d917fbbba78300a82a1ccb4cff/i-img900x1200-1726781142135775mene871624.jpg?pri=l&w=300&h=300&up=0&nf_src=sy&nf_path=images/auc/pc/top/image/1.0.3/na_170x170.png&nf_st=200",
      "target_m_price": "8,000円",
      "time_m": 120,
      "needs_photo_check": true,
      "is_white_sneaker": false,
      "needs_sole_warning": false,
      "keyword": "コールハーン シューズ"
    },
    {
      "title": "genten ゲンテン レザーポーチ 透かしカットワークデザイン ブラウン系",
      "url": "https://auctions.yahoo.co.jp/jp/auction/p1229214282",
      "price_formatted": "6,600円",
      "profit_formatted": "2,350円",
      "expected_profit": 2350,
      "stars": "★★★☆☆",
      "condition": "やや傷や汚れあり / サイズ: 判定不要",
      "remaining_time": "22時間",
      "img_url": "https://auc-pctr.c.yimg.jp/i/auctions.c.yimg.jp/images.auctions.yahoo.co.jp/image/dr000/auc0205/user/4de85e37f2cc010ee64b5d765ea5758a79581da8e31f1e79dbb068181bd11d56/i-img1200x900-17782344313771khvdbx89663.jpg?pri=l&w=300&h=300&up=0&nf_src=sy&nf_path=images/auc/pc/top/image/1.0.3/na_170x170.png&nf_st=200",
      "target_m_price": "12,000円",
      "time_m": 1320,
      "needs_photo_check": true,
      "is_white_sneaker": false,
      "needs_sole_warning": false,
      "keyword": "ゲンテン カットワーク"
    },
    {
      "title": "genten カットワーク 長財布 ロングウォレット L字ファスナー レザー ブラウン",
      "url": "https://auctions.yahoo.co.jp/jp/auction/q1190780481",
      "price_formatted": "6,600円",
      "profit_formatted": "2,350円",
      "expected_profit": 2350,
      "stars": "★★★☆☆",
      "condition": "やや傷や汚れあり / サイズ: 判定不要",
      "remaining_time": "22時間",
      "img_url": "https://auc-pctr.c.yimg.jp/i/auctions.c.yimg.jp/images.auctions.yahoo.co.jp/image/dr000/auc0106/user/4de85e37f2cc010ee64b5d765ea5758a79581da8e31f1e79dbb068181bd11d56/i-img1200x900-17512641964202p2strn24115.jpg?pri=l&w=300&h=300&up=0&nf_src=sy&nf_path=images/auc/pc/top/image/1.0.3/na_170x170.png&nf_st=200",
      "target_m_price": "12,000円",
      "time_m": 1320,
      "needs_photo_check": true,
      "is_white_sneaker": false,
      "needs_sole_warning": false,
      "keyword": "ゲンテン カットワーク"
    },
    {
      "title": "コーチ ワンショルダーバッグ 9210 ブラック レザー 中古 肩掛け オールレザー ヴィンテージ オールド 鞄 レディース",
      "url": "https://auctions.yahoo.co.jp/jp/auction/b1205314162",
      "price_formatted": "12,290円",
      "profit_formatted": "2,060円",
      "expected_profit": 2060,
      "stars": "★★★☆☆",
      "condition": "未使用に近い / サイズ: 判定不要",
      "remaining_time": "17時間",
      "img_url": "https://auc-pctr.c.yimg.jp/i/auctions.c.yimg.jp/images.auctions.yahoo.co.jp/image/dr000/auc0110/user/e6589c0484641d08fb87fa70ca2ffa9ed5938f6371c52b5c4b67d75b28428b18/i-img1000x1000-17613807498604d3n6482425.jpg?pri=l&w=300&h=300&up=0&nf_src=sy&nf_path=images/auc/pc/top/image/1.0.3/na_170x170.png&nf_st=200",
      "target_m_price": "18,000円",
      "time_m": 1020,
      "needs_photo_check": false,
      "is_white_sneaker": false,
      "needs_sole_warning": false,
      "keyword": "オールドコーチ"
    },
    {
      "title": "ペリーコ PELLICO サニー SUNNY サンダル エスパドリーユ ウエッジソール 37 グレー /ka0521 レディース",
      "url": "https://auctions.yahoo.co.jp/jp/auction/1184193135",
      "price_formatted": "1,700円",
      "profit_formatted": "1,850円",
      "expected_profit": 1850,
      "stars": "★★★☆☆",
      "condition": "やや傷や汚れあり",
      "remaining_time": "3時間",
      "img_url": "https://auc-pctr.c.yimg.jp/i/auctions.c.yimg.jp/images.auctions.yahoo.co.jp/image/dr000/auc0105/user/1a5ffb9ea9b949dff605eef2dc10bfee6dd43115da2aeab12bda98ae99737110/i-img640x427-17467885652530u350kc55193.jpg?pri=l&w=300&h=300&up=0&nf_src=sy&nf_path=images/auc/pc/top/image/1.0.3/na_170x170.png&nf_st=200",
      "target_m_price": "6,000円",
      "time_m": 180,
      "needs_photo_check": true,
      "is_white_sneaker": false,
      "needs_sole_warning": false,
      "keyword": "ペリーコ シューズ"
    },
    {
      "title": "FURLA◆3つ折り財布/レザー/BLU/無地/レディース",
      "url": "https://auctions.yahoo.co.jp/jp/auction/c1216355778",
      "price_formatted": "7,260円",
      "profit_formatted": "1,770円",
      "expected_profit": 1770,
      "stars": "★★★☆☆",
      "condition": "未使用に近い / サイズ: 判定不要",
      "remaining_time": "41分50秒",
      "img_url": "https://auc-pctr.c.yimg.jp/i/auctions.c.yimg.jp/images.auctions.yahoo.co.jp/image/dr000/auc0201/user/3641761cb5965ae1c25e46fef128dc48024c74d917fbbba78300a82a1ccb4cff/i-img900x1200-1768682142657271jkbc78501.jpg?pri=l&w=300&h=300&up=0&nf_src=sy&nf_path=images/auc/pc/top/image/1.0.3/na_170x170.png&nf_st=200",
      "target_m_price": "11,000円",
      "time_m": 41,
      "needs_photo_check": false,
      "is_white_sneaker": false,
      "needs_sole_warning": false,
      "keyword": "フルラ 財布"
    },
    {
      "title": "FURLA◆コンパクト/シレナ/3つ折り財布/レザー/PNK/無地/レディース",
      "url": "https://auctions.yahoo.co.jp/jp/auction/j1189764177",
      "price_formatted": "7,260円",
      "profit_formatted": "1,770円",
      "expected_profit": 1770,
      "stars": "★★★☆☆",
      "condition": "未使用に近い / サイズ: 判定不要",
      "remaining_time": "4時間",
      "img_url": "https://auc-pctr.c.yimg.jp/i/auctions.c.yimg.jp/images.auctions.yahoo.co.jp/image/dr000/auc0106/user/3641761cb5965ae1c25e46fef128dc48024c74d917fbbba78300a82a1ccb4cff/i-img900x1200-17505521218262rptiio3466.jpg?pri=l&w=300&h=300&up=0&nf_src=sy&nf_path=images/auc/pc/top/image/1.0.3/na_170x170.png&nf_st=200",
      "target_m_price": "11,000円",
      "time_m": 240,
      "needs_photo_check": false,
      "is_white_sneaker": false,
      "needs_sole_warning": false,
      "keyword": "フルラ 財布"
    },
    {
      "title": "COLE HAAN コールハーン ブーティ ザ ゴートゥー パーク アンクル ブーツ 65MM スエード サイドゴア",
      "url": "https://auctions.yahoo.co.jp/jp/auction/q1231303815",
      "price_formatted": "3,700円",
      "profit_formatted": "1,650円",
      "expected_profit": 1650,
      "stars": "★★★☆☆",
      "condition": "やや傷や汚れあり",
      "remaining_time": "2時間",
      "img_url": "https://auc-pctr.c.yimg.jp/i/auctions.c.yimg.jp/images.auctions.yahoo.co.jp/image/dr000/auc0205/user/f59cc71887dc0d337143225ccf0c0585f08a7e9b799e08585c359779385c0953/i-img1000x1000-177980767258775dzw5p4218.jpg?pri=l&w=300&h=300&up=0&nf_src=sy&nf_path=images/auc/pc/top/image/1.0.3/na_170x170.png&nf_st=200",
      "target_m_price": "8,000円",
      "time_m": 120,
      "needs_photo_check": true,
      "is_white_sneaker": false,
      "needs_sole_warning": false,
      "keyword": "コールハーン シューズ"
    },
    {
      "title": "agnes b.VOYAGE de luxe アニエスベー レザー 三つ折り 財布 がま口 本革 [S210197]",
      "url": "https://auctions.yahoo.co.jp/jp/auction/b1224729341",
      "price_formatted": "2,000円",
      "profit_formatted": "1,630円",
      "expected_profit": 1630,
      "stars": "★★★☆☆",
      "condition": "やや傷や汚れあり / サイズ: 判定不要",
      "remaining_time": "21時間",
      "img_url": "https://auc-pctr.c.yimg.jp/i/auctions.c.yimg.jp/images.auctions.yahoo.co.jp/image/dr000/auc0203/user/ef6aefbecf3d0b14837dcf2193bb5ac8a2ddadaa02866082826c3cffc3b15649/i-img1200x1200-17748644942053rw5yoi27.jpg?pri=l&w=300&h=300&up=0&nf_src=sy&nf_path=images/auc/pc/top/image/1.0.3/na_170x170.png&nf_st=200",
      "target_m_price": "5,000円",
      "time_m": 1260,
      "needs_photo_check": true,
      "is_white_sneaker": false,
      "needs_sole_warning": false,
      "keyword": "アニエスベー がま口"
    }
  ],
  "price_last_update": "2026年06月07日 00:49"
}